Compiled from "LivingEntityRenderer.java"
public abstract class net.minecraft.client.renderer.entity.LivingEntityRenderer<T extends net.minecraft.world.entity.LivingEntity, M extends net.minecraft.client.model.EntityModel<T>> extends net.minecraft.client.renderer.entity.EntityRenderer<T> implements net.minecraft.client.renderer.entity.RenderLayerParent<T, M> {
  private static final org.slf4j.Logger LOGGER;

  private static final float EYE_BED_OFFSET;

  protected M model;

  protected final java.util.List<net.minecraft.client.renderer.entity.layers.RenderLayer<T, M>> layers;

  public net.minecraft.client.renderer.entity.LivingEntityRenderer(net.minecraft.client.renderer.entity.EntityRendererProvider$Context, M, float);
    Code:
       0: aload_0
       1: aload_1
       2: invokespecial #40                 // Method net/minecraft/client/renderer/entity/EntityRenderer."<init>":(Lnet/minecraft/client/renderer/entity/EntityRendererProvider$Context;)V
       5: aload_0
       6: invokestatic  #46                 // Method com/google/common/collect/Lists.newArrayList:()Ljava/util/ArrayList;
       9: putfield      #48                 // Field layers:Ljava/util/List;
      12: aload_0
      13: aload_2
      14: putfield      #50                 // Field model:Lnet/minecraft/client/model/EntityModel;
      17: aload_0
      18: fload_3
      19: putfield      #53                 // Field shadowRadius:F
      22: return

  protected final boolean addLayer(net.minecraft.client.renderer.entity.layers.RenderLayer<T, M>);
    Code:
       0: aload_0
       1: getfield      #48                 // Field layers:Ljava/util/List;
       4: aload_1
       5: invokeinterface #67,  2           // InterfaceMethod java/util/List.add:(Ljava/lang/Object;)Z
      10: ireturn

  public M getModel();
    Code:
       0: aload_0
       1: getfield      #50                 // Field model:Lnet/minecraft/client/model/EntityModel;
       4: areturn

  public void render(T, float, float, com.mojang.blaze3d.vertex.PoseStack, net.minecraft.client.renderer.MultiBufferSource, int);
    Code:
       0: aload         4
       2: invokevirtual #86                 // Method com/mojang/blaze3d/vertex/PoseStack.pushPose:()V
       5: aload_0
       6: getfield      #50                 // Field model:Lnet/minecraft/client/model/EntityModel;
       9: aload_0
      10: aload_1
      11: fload_3
      12: invokevirtual #90                 // Method getAttackAnim:(Lnet/minecraft/world/entity/LivingEntity;F)F
      15: putfield      #95                 // Field net/minecraft/client/model/EntityModel.attackTime:F
      18: aload_0
      19: getfield      #50                 // Field model:Lnet/minecraft/client/model/EntityModel;
      22: aload_1
      23: invokevirtual #101                // Method net/minecraft/world/entity/LivingEntity.isPassenger:()Z
      26: putfield      #105                // Field net/minecraft/client/model/EntityModel.riding:Z
      29: aload_0
      30: getfield      #50                 // Field model:Lnet/minecraft/client/model/EntityModel;
      33: aload_1
      34: invokevirtual #108                // Method net/minecraft/world/entity/LivingEntity.isBaby:()Z
      37: putfield      #111                // Field net/minecraft/client/model/EntityModel.young:Z
      40: fload_3
      41: aload_1
      42: getfield      #114                // Field net/minecraft/world/entity/LivingEntity.yBodyRotO:F
      45: aload_1
      46: getfield      #117                // Field net/minecraft/world/entity/LivingEntity.yBodyRot:F
      49: invokestatic  #123                // Method net/minecraft/util/Mth.rotLerp:(FFF)F
      52: fstore        7
      54: fload_3
      55: aload_1
      56: getfield      #126                // Field net/minecraft/world/entity/LivingEntity.yHeadRotO:F
      59: aload_1
      60: getfield      #129                // Field net/minecraft/world/entity/LivingEntity.yHeadRot:F
      63: invokestatic  #123                // Method net/minecraft/util/Mth.rotLerp:(FFF)F
      66: fstore        8
      68: fload         8
      70: fload         7
      72: fsub
      73: fstore        9
      75: aload_1
      76: invokevirtual #101                // Method net/minecraft/world/entity/LivingEntity.isPassenger:()Z
      79: ifeq          192
      82: aload_1
      83: invokevirtual #133                // Method net/minecraft/world/entity/LivingEntity.getVehicle:()Lnet/minecraft/world/entity/Entity;
      86: astore        11
      88: aload         11
      90: instanceof    #97                 // class net/minecraft/world/entity/LivingEntity
      93: ifeq          192
      96: aload         11
      98: checkcast     #97                 // class net/minecraft/world/entity/LivingEntity
     101: astore        10
     103: fload_3
     104: aload         10
     106: getfield      #114                // Field net/minecraft/world/entity/LivingEntity.yBodyRotO:F
     109: aload         10
     111: getfield      #117                // Field net/minecraft/world/entity/LivingEntity.yBodyRot:F
     114: invokestatic  #123                // Method net/minecraft/util/Mth.rotLerp:(FFF)F
     117: fstore        7
     119: fload         8
     121: fload         7
     123: fsub
     124: fstore        9
     126: fload         9
     128: invokestatic  #137                // Method net/minecraft/util/Mth.wrapDegrees:(F)F
     131: fstore        11
     133: fload         11
     135: ldc           #138                // float -85.0f
     137: fcmpg
     138: ifge          145
     141: ldc           #138                // float -85.0f
     143: fstore        11
     145: fload         11
     147: ldc           #141                // float 85.0f
     149: fcmpl
     150: iflt          157
     153: ldc           #141                // float 85.0f
     155: fstore        11
     157: fload         8
     159: fload         11
     161: fsub
     162: fstore        7
     164: fload         11
     166: fload         11
     168: fmul
     169: ldc           #142                // float 2500.0f
     171: fcmpl
     172: ifle          185
     175: fload         7
     177: fload         11
     179: ldc           #143                // float 0.2f
     181: fmul
     182: fadd
     183: fstore        7
     185: fload         8
     187: fload         7
     189: fsub
     190: fstore        9
     192: fload_3
     193: aload_1
     194: getfield      #146                // Field net/minecraft/world/entity/LivingEntity.xRotO:F
     197: aload_1
     198: invokevirtual #150                // Method net/minecraft/world/entity/LivingEntity.getXRot:()F
     201: invokestatic  #153                // Method net/minecraft/util/Mth.lerp:(FFF)F
     204: fstore        10
     206: aload_1
     207: invokestatic  #157                // Method isEntityUpsideDown:(Lnet/minecraft/world/entity/LivingEntity;)Z
     210: ifeq          227
     213: fload         10
     215: ldc           #158                // float -1.0f
     217: fmul
     218: fstore        10
     220: fload         9
     222: ldc           #158                // float -1.0f
     224: fmul
     225: fstore        9
     227: fload         9
     229: invokestatic  #137                // Method net/minecraft/util/Mth.wrapDegrees:(F)F
     232: fstore        9
     234: aload_1
     235: getstatic     #164                // Field net/minecraft/world/entity/Pose.SLEEPING:Lnet/minecraft/world/entity/Pose;
     238: invokevirtual #168                // Method net/minecraft/world/entity/LivingEntity.hasPose:(Lnet/minecraft/world/entity/Pose;)Z
     241: ifeq          293
     244: aload_1
     245: invokevirtual #172                // Method net/minecraft/world/entity/LivingEntity.getBedOrientation:()Lnet/minecraft/core/Direction;
     248: astore        11
     250: aload         11
     252: ifnull        293
     255: aload_1
     256: getstatic     #175                // Field net/minecraft/world/entity/Pose.STANDING:Lnet/minecraft/world/entity/Pose;
     259: invokevirtual #179                // Method net/minecraft/world/entity/LivingEntity.getEyeHeight:(Lnet/minecraft/world/entity/Pose;)F
     262: ldc           #25                 // float 0.1f
     264: fsub
     265: fstore        12
     267: aload         4
     269: aload         11
     271: invokevirtual #185                // Method net/minecraft/core/Direction.getStepX:()I
     274: ineg
     275: i2f
     276: fload         12
     278: fmul
     279: fconst_0
     280: aload         11
     282: invokevirtual #188                // Method net/minecraft/core/Direction.getStepZ:()I
     285: ineg
     286: i2f
     287: fload         12
     289: fmul
     290: invokevirtual #192                // Method com/mojang/blaze3d/vertex/PoseStack.translate:(FFF)V
     293: aload_1
     294: invokevirtual #195                // Method net/minecraft/world/entity/LivingEntity.getScale:()F
     297: fstore        11
     299: aload         4
     301: fload         11
     303: fload         11
     305: fload         11
     307: invokevirtual #198                // Method com/mojang/blaze3d/vertex/PoseStack.scale:(FFF)V
     310: aload_0
     311: aload_1
     312: fload_3
     313: invokevirtual #201                // Method getBob:(Lnet/minecraft/world/entity/LivingEntity;F)F
     316: fstore        12
     318: aload_0
     319: aload_1
     320: aload         4
     322: fload         12
     324: fload         7
     326: fload_3
     327: fload         11
     329: invokevirtual #205                // Method setupRotations:(Lnet/minecraft/world/entity/LivingEntity;Lcom/mojang/blaze3d/vertex/PoseStack;FFFF)V
     332: aload         4
     334: ldc           #158                // float -1.0f
     336: ldc           #158                // float -1.0f
     338: fconst_1
     339: invokevirtual #198                // Method com/mojang/blaze3d/vertex/PoseStack.scale:(FFF)V
     342: aload_0
     343: aload_1
     344: aload         4
     346: fload_3
     347: invokevirtual #208                // Method scale:(Lnet/minecraft/world/entity/LivingEntity;Lcom/mojang/blaze3d/vertex/PoseStack;F)V
     350: aload         4
     352: fconst_0
     353: ldc           #209                // float -1.501f
     355: fconst_0
     356: invokevirtual #192                // Method com/mojang/blaze3d/vertex/PoseStack.translate:(FFF)V
     359: fconst_0
     360: fstore        13
     362: fconst_0
     363: fstore        14
     365: aload_1
     366: invokevirtual #101                // Method net/minecraft/world/entity/LivingEntity.isPassenger:()Z
     369: ifne          423
     372: aload_1
     373: invokevirtual #212                // Method net/minecraft/world/entity/LivingEntity.isAlive:()Z
     376: ifeq          423
     379: aload_1
     380: getfield      #216                // Field net/minecraft/world/entity/LivingEntity.walkAnimation:Lnet/minecraft/world/entity/WalkAnimationState;
     383: fload_3
     384: invokevirtual #221                // Method net/minecraft/world/entity/WalkAnimationState.speed:(F)F
     387: fstore        13
     389: aload_1
     390: getfield      #216                // Field net/minecraft/world/entity/LivingEntity.walkAnimation:Lnet/minecraft/world/entity/WalkAnimationState;
     393: fload_3
     394: invokevirtual #224                // Method net/minecraft/world/entity/WalkAnimationState.position:(F)F
     397: fstore        14
     399: aload_1
     400: invokevirtual #108                // Method net/minecraft/world/entity/LivingEntity.isBaby:()Z
     403: ifeq          413
     406: fload         14
     408: ldc           #225                // float 3.0f
     410: fmul
     411: fstore        14
     413: fload         13
     415: fconst_1
     416: fcmpl
     417: ifle          423
     420: fconst_1
     421: fstore        13
     423: aload_0
     424: getfield      #50                 // Field model:Lnet/minecraft/client/model/EntityModel;
     427: aload_1
     428: fload         14
     430: fload         13
     432: fload_3
     433: invokevirtual #229                // Method net/minecraft/client/model/EntityModel.prepareMobModel:(Lnet/minecraft/world/entity/Entity;FFF)V
     436: aload_0
     437: getfield      #50                 // Field model:Lnet/minecraft/client/model/EntityModel;
     440: aload_1
     441: fload         14
     443: fload         13
     445: fload         12
     447: fload         9
     449: fload         10
     451: invokevirtual #233                // Method net/minecraft/client/model/EntityModel.setupAnim:(Lnet/minecraft/world/entity/Entity;FFFFF)V
     454: invokestatic  #239                // Method net/minecraft/client/Minecraft.getInstance:()Lnet/minecraft/client/Minecraft;
     457: astore        15
     459: aload_0
     460: aload_1
     461: invokevirtual #242                // Method isBodyVisible:(Lnet/minecraft/world/entity/LivingEntity;)Z
     464: istore        16
     466: iload         16
     468: ifne          487
     471: aload_1
     472: aload         15
     474: getfield      #246                // Field net/minecraft/client/Minecraft.player:Lnet/minecraft/client/player/LocalPlayer;
     477: invokevirtual #250                // Method net/minecraft/world/entity/LivingEntity.isInvisibleTo:(Lnet/minecraft/world/entity/player/Player;)Z
     480: ifne          487
     483: iconst_1
     484: goto          488
     487: iconst_0
     488: istore        17
     490: aload         15
     492: aload_1
     493: invokevirtual #254                // Method net/minecraft/client/Minecraft.shouldEntityAppearGlowing:(Lnet/minecraft/world/entity/Entity;)Z
     496: istore        18
     498: aload_0
     499: aload_1
     500: iload         16
     502: iload         17
     504: iload         18
     506: invokevirtual #258                // Method getRenderType:(Lnet/minecraft/world/entity/LivingEntity;ZZZ)Lnet/minecraft/client/renderer/RenderType;
     509: astore        19
     511: aload         19
     513: ifnull        566
     516: aload         5
     518: aload         19
     520: invokeinterface #262,  2          // InterfaceMethod net/minecraft/client/renderer/MultiBufferSource.getBuffer:(Lnet/minecraft/client/renderer/RenderType;)Lcom/mojang/blaze3d/vertex/VertexConsumer;
     525: astore        20
     527: aload_1
     528: aload_0
     529: aload_1
     530: fload_3
     531: invokevirtual #265                // Method getWhiteOverlayProgress:(Lnet/minecraft/world/entity/LivingEntity;F)F
     534: invokestatic  #269                // Method getOverlayCoords:(Lnet/minecraft/world/entity/LivingEntity;F)I
     537: istore        21
     539: aload_0
     540: getfield      #50                 // Field model:Lnet/minecraft/client/model/EntityModel;
     543: aload         4
     545: aload         20
     547: iload         6
     549: iload         21
     551: iload         17
     553: ifeq          562
     556: ldc_w         #270                // int 654311423
     559: goto          563
     562: iconst_m1
     563: invokevirtual #276                // Method net/minecraft/client/model/EntityModel.renderToBuffer:(Lcom/mojang/blaze3d/vertex/PoseStack;Lcom/mojang/blaze3d/vertex/VertexConsumer;III)V
     566: aload_1
     567: invokevirtual #279                // Method net/minecraft/world/entity/LivingEntity.isSpectator:()Z
     570: ifne          632
     573: aload_0
     574: getfield      #48                 // Field layers:Ljava/util/List;
     577: invokeinterface #283,  1          // InterfaceMethod java/util/List.iterator:()Ljava/util/Iterator;
     582: astore        20
     584: aload         20
     586: invokeinterface #288,  1          // InterfaceMethod java/util/Iterator.hasNext:()Z
     591: ifeq          632
     594: aload         20
     596: invokeinterface #292,  1          // InterfaceMethod java/util/Iterator.next:()Ljava/lang/Object;
     601: checkcast     #294                // class net/minecraft/client/renderer/entity/layers/RenderLayer
     604: astore        21
     606: aload         21
     608: aload         4
     610: aload         5
     612: iload         6
     614: aload_1
     615: fload         14
     617: fload         13
     619: fload_3
     620: fload         12
     622: fload         9
     624: fload         10
     626: invokevirtual #297                // Method net/minecraft/client/renderer/entity/layers/RenderLayer.render:(Lcom/mojang/blaze3d/vertex/PoseStack;Lnet/minecraft/client/renderer/MultiBufferSource;ILnet/minecraft/world/entity/Entity;FFFFFF)V
     629: goto          584
     632: aload         4
     634: invokevirtual #300                // Method com/mojang/blaze3d/vertex/PoseStack.popPose:()V
     637: aload_0
     638: aload_1
     639: fload_2
     640: fload_3
     641: aload         4
     643: aload         5
     645: iload         6
     647: invokespecial #303                // Method net/minecraft/client/renderer/entity/EntityRenderer.render:(Lnet/minecraft/world/entity/Entity;FFLcom/mojang/blaze3d/vertex/PoseStack;Lnet/minecraft/client/renderer/MultiBufferSource;I)V
     650: return

  protected net.minecraft.client.renderer.RenderType getRenderType(T, boolean, boolean, boolean);
    Code:
       0: aload_0
       1: aload_1
       2: invokevirtual #335                // Method getTextureLocation:(Lnet/minecraft/world/entity/Entity;)Lnet/minecraft/resources/ResourceLocation;
       5: astore        5
       7: iload_3
       8: ifeq          17
      11: aload         5
      13: invokestatic  #341                // Method net/minecraft/client/renderer/RenderType.itemEntityTranslucentCull:(Lnet/minecraft/resources/ResourceLocation;)Lnet/minecraft/client/renderer/RenderType;
      16: areturn
      17: iload_2
      18: ifeq          31
      21: aload_0
      22: getfield      #50                 // Field model:Lnet/minecraft/client/model/EntityModel;
      25: aload         5
      27: invokevirtual #345                // Method net/minecraft/client/model/EntityModel.renderType:(Lnet/minecraft/resources/ResourceLocation;)Lnet/minecraft/client/renderer/RenderType;
      30: areturn
      31: iload         4
      33: ifeq          42
      36: aload         5
      38: invokestatic  #348                // Method net/minecraft/client/renderer/RenderType.outline:(Lnet/minecraft/resources/ResourceLocation;)Lnet/minecraft/client/renderer/RenderType;
      41: areturn
      42: aconst_null
      43: areturn

  public static int getOverlayCoords(net.minecraft.world.entity.LivingEntity, float);
    Code:
       0: fload_1
       1: invokestatic  #356                // Method net/minecraft/client/renderer/texture/OverlayTexture.u:(F)I
       4: aload_0
       5: getfield      #359                // Field net/minecraft/world/entity/LivingEntity.hurtTime:I
       8: ifgt          18
      11: aload_0
      12: getfield      #362                // Field net/minecraft/world/entity/LivingEntity.deathTime:I
      15: ifle          22
      18: iconst_1
      19: goto          23
      22: iconst_0
      23: invokestatic  #366                // Method net/minecraft/client/renderer/texture/OverlayTexture.v:(Z)I
      26: invokestatic  #370                // Method net/minecraft/client/renderer/texture/OverlayTexture.pack:(II)I
      29: ireturn

  protected boolean isBodyVisible(T);
    Code:
       0: aload_1
       1: invokevirtual #374                // Method net/minecraft/world/entity/LivingEntity.isInvisible:()Z
       4: ifne          11
       7: iconst_1
       8: goto          12
      11: iconst_0
      12: ireturn

  private static float sleepDirectionToRotation(net.minecraft.core.Direction);
    Code:
       0: getstatic     #380                // Field net/minecraft/client/renderer/entity/LivingEntityRenderer$1.$SwitchMap$net$minecraft$core$Direction:[I
       3: aload_0
       4: invokevirtual #383                // Method net/minecraft/core/Direction.ordinal:()I
       7: iaload
       8: tableswitch   { // 1 to 4
                     1: 40
                     2: 44
                     3: 46
                     4: 50
               default: 54
          }
      40: ldc_w         #384                // float 90.0f
      43: freturn
      44: fconst_0
      45: freturn
      46: ldc_w         #385                // float 270.0f
      49: freturn
      50: ldc_w         #386                // float 180.0f
      53: freturn
      54: fconst_0
      55: freturn

  protected boolean isShaking(T);
    Code:
       0: aload_1
       1: invokevirtual #390                // Method net/minecraft/world/entity/LivingEntity.isFullyFrozen:()Z
       4: ireturn

  protected void setupRotations(T, com.mojang.blaze3d.vertex.PoseStack, float, float, float, float);
    Code:
       0: aload_0
       1: aload_1
       2: invokevirtual #393                // Method isShaking:(Lnet/minecraft/world/entity/LivingEntity;)Z
       5: ifeq          34
       8: fload         4
      10: aload_1
      11: getfield      #396                // Field net/minecraft/world/entity/LivingEntity.tickCount:I
      14: i2d
      15: ldc2_w        #397                // double 3.25d
      18: dmul
      19: invokestatic  #404                // Method java/lang/Math.cos:(D)D
      22: ldc2_w        #405                // double 3.141592653589793d
      25: dmul
      26: ldc2_w        #407                // double 0.4000000059604645d
      29: dmul
      30: d2f
      31: fadd
      32: fstore        4
      34: aload_1
      35: getstatic     #164                // Field net/minecraft/world/entity/Pose.SLEEPING:Lnet/minecraft/world/entity/Pose;
      38: invokevirtual #168                // Method net/minecraft/world/entity/LivingEntity.hasPose:(Lnet/minecraft/world/entity/Pose;)Z
      41: ifne          62
      44: aload_2
      45: getstatic     #414                // Field com/mojang/math/Axis.YP:Lcom/mojang/math/Axis;
      48: ldc_w         #386                // float 180.0f
      51: fload         4
      53: fsub
      54: invokeinterface #418,  2          // InterfaceMethod com/mojang/math/Axis.rotationDegrees:(F)Lorg/joml/Quaternionf;
      59: invokevirtual #422                // Method com/mojang/blaze3d/vertex/PoseStack.mulPose:(Lorg/joml/Quaternionf;)V
      62: aload_1
      63: getfield      #362                // Field net/minecraft/world/entity/LivingEntity.deathTime:I
      66: ifle          129
      69: aload_1
      70: getfield      #362                // Field net/minecraft/world/entity/LivingEntity.deathTime:I
      73: i2f
      74: fload         5
      76: fadd
      77: fconst_1
      78: fsub
      79: ldc_w         #423                // float 20.0f
      82: fdiv
      83: ldc_w         #424                // float 1.6f
      86: fmul
      87: fstore        7
      89: fload         7
      91: invokestatic  #427                // Method net/minecraft/util/Mth.sqrt:(F)F
      94: fstore        7
      96: fload         7
      98: fconst_1
      99: fcmpl
     100: ifle          106
     103: fconst_1
     104: fstore        7
     106: aload_2
     107: getstatic     #430                // Field com/mojang/math/Axis.ZP:Lcom/mojang/math/Axis;
     110: fload         7
     112: aload_0
     113: aload_1
     114: invokevirtual #434                // Method getFlipDegrees:(Lnet/minecraft/world/entity/LivingEntity;)F
     117: fmul
     118: invokeinterface #418,  2          // InterfaceMethod com/mojang/math/Axis.rotationDegrees:(F)Lorg/joml/Quaternionf;
     123: invokevirtual #422                // Method com/mojang/blaze3d/vertex/PoseStack.mulPose:(Lorg/joml/Quaternionf;)V
     126: goto          303
     129: aload_1
     130: invokevirtual #437                // Method net/minecraft/world/entity/LivingEntity.isAutoSpinAttack:()Z
     133: ifeq          183
     136: aload_2
     137: getstatic     #440                // Field com/mojang/math/Axis.XP:Lcom/mojang/math/Axis;
     140: ldc_w         #441                // float -90.0f
     143: aload_1
     144: invokevirtual #150                // Method net/minecraft/world/entity/LivingEntity.getXRot:()F
     147: fsub
     148: invokeinterface #418,  2          // InterfaceMethod com/mojang/math/Axis.rotationDegrees:(F)Lorg/joml/Quaternionf;
     153: invokevirtual #422                // Method com/mojang/blaze3d/vertex/PoseStack.mulPose:(Lorg/joml/Quaternionf;)V
     156: aload_2
     157: getstatic     #414                // Field com/mojang/math/Axis.YP:Lcom/mojang/math/Axis;
     160: aload_1
     161: getfield      #396                // Field net/minecraft/world/entity/LivingEntity.tickCount:I
     164: i2f
     165: fload         5
     167: fadd
     168: ldc_w         #442                // float -75.0f
     171: fmul
     172: invokeinterface #418,  2          // InterfaceMethod com/mojang/math/Axis.rotationDegrees:(F)Lorg/joml/Quaternionf;
     177: invokevirtual #422                // Method com/mojang/blaze3d/vertex/PoseStack.mulPose:(Lorg/joml/Quaternionf;)V
     180: goto          303
     183: aload_1
     184: getstatic     #164                // Field net/minecraft/world/entity/Pose.SLEEPING:Lnet/minecraft/world/entity/Pose;
     187: invokevirtual #168                // Method net/minecraft/world/entity/LivingEntity.hasPose:(Lnet/minecraft/world/entity/Pose;)Z
     190: ifeq          265
     193: aload_1
     194: invokevirtual #172                // Method net/minecraft/world/entity/LivingEntity.getBedOrientation:()Lnet/minecraft/core/Direction;
     197: astore        7
     199: aload         7
     201: ifnull        212
     204: aload         7
     206: invokestatic  #444                // Method sleepDirectionToRotation:(Lnet/minecraft/core/Direction;)F
     209: goto          214
     212: fload         4
     214: fstore        8
     216: aload_2
     217: getstatic     #414                // Field com/mojang/math/Axis.YP:Lcom/mojang/math/Axis;
     220: fload         8
     222: invokeinterface #418,  2          // InterfaceMethod com/mojang/math/Axis.rotationDegrees:(F)Lorg/joml/Quaternionf;
     227: invokevirtual #422                // Method com/mojang/blaze3d/vertex/PoseStack.mulPose:(Lorg/joml/Quaternionf;)V
     230: aload_2
     231: getstatic     #430                // Field com/mojang/math/Axis.ZP:Lcom/mojang/math/Axis;
     234: aload_0
     235: aload_1
     236: invokevirtual #434                // Method getFlipDegrees:(Lnet/minecraft/world/entity/LivingEntity;)F
     239: invokeinterface #418,  2          // InterfaceMethod com/mojang/math/Axis.rotationDegrees:(F)Lorg/joml/Quaternionf;
     244: invokevirtual #422                // Method com/mojang/blaze3d/vertex/PoseStack.mulPose:(Lorg/joml/Quaternionf;)V
     247: aload_2
     248: getstatic     #414                // Field com/mojang/math/Axis.YP:Lcom/mojang/math/Axis;
     251: ldc_w         #385                // float 270.0f
     254: invokeinterface #418,  2          // InterfaceMethod com/mojang/math/Axis.rotationDegrees:(F)Lorg/joml/Quaternionf;
     259: invokevirtual #422                // Method com/mojang/blaze3d/vertex/PoseStack.mulPose:(Lorg/joml/Quaternionf;)V
     262: goto          303
     265: aload_1
     266: invokestatic  #157                // Method isEntityUpsideDown:(Lnet/minecraft/world/entity/LivingEntity;)Z
     269: ifeq          303
     272: aload_2
     273: fconst_0
     274: aload_1
     275: invokevirtual #447                // Method net/minecraft/world/entity/LivingEntity.getBbHeight:()F
     278: ldc           #25                 // float 0.1f
     280: fadd
     281: fload         6
     283: fdiv
     284: fconst_0
     285: invokevirtual #192                // Method com/mojang/blaze3d/vertex/PoseStack.translate:(FFF)V
     288: aload_2
     289: getstatic     #430                // Field com/mojang/math/Axis.ZP:Lcom/mojang/math/Axis;
     292: ldc_w         #386                // float 180.0f
     295: invokeinterface #418,  2          // InterfaceMethod com/mojang/math/Axis.rotationDegrees:(F)Lorg/joml/Quaternionf;
     300: invokevirtual #422                // Method com/mojang/blaze3d/vertex/PoseStack.mulPose:(Lorg/joml/Quaternionf;)V
     303: return

  protected float getAttackAnim(T, float);
    Code:
       0: aload_1
       1: fload_2
       2: invokevirtual #450                // Method net/minecraft/world/entity/LivingEntity.getAttackAnim:(F)F
       5: freturn

  protected float getBob(T, float);
    Code:
       0: aload_1
       1: getfield      #396                // Field net/minecraft/world/entity/LivingEntity.tickCount:I
       4: i2f
       5: fload_2
       6: fadd
       7: freturn

  protected float getFlipDegrees(T);
    Code:
       0: ldc_w         #384                // float 90.0f
       3: freturn

  protected float getWhiteOverlayProgress(T, float);
    Code:
       0: fconst_0
       1: freturn

  protected void scale(T, com.mojang.blaze3d.vertex.PoseStack, float);
    Code:
       0: return

  protected boolean shouldShowName(T);
    Code:
       0: aload_0
       1: getfield      #457                // Field entityRenderDispatcher:Lnet/minecraft/client/renderer/entity/EntityRenderDispatcher;
       4: aload_1
       5: invokevirtual #463                // Method net/minecraft/client/renderer/entity/EntityRenderDispatcher.distanceToSqr:(Lnet/minecraft/world/entity/Entity;)D
       8: dstore_2
       9: aload_1
      10: invokevirtual #466                // Method net/minecraft/world/entity/LivingEntity.isDiscrete:()Z
      13: ifeq          22
      16: ldc_w         #467                // float 32.0f
      19: goto          25
      22: ldc_w         #468                // float 64.0f
      25: fstore        4
      27: dload_2
      28: fload         4
      30: fload         4
      32: fmul
      33: f2d
      34: dcmpl
      35: iflt          40
      38: iconst_0
      39: ireturn
      40: invokestatic  #239                // Method net/minecraft/client/Minecraft.getInstance:()Lnet/minecraft/client/Minecraft;
      43: astore        5
      45: aload         5
      47: getfield      #246                // Field net/minecraft/client/Minecraft.player:Lnet/minecraft/client/player/LocalPlayer;
      50: astore        6
      52: aload_1
      53: aload         6
      55: invokevirtual #250                // Method net/minecraft/world/entity/LivingEntity.isInvisibleTo:(Lnet/minecraft/world/entity/player/Player;)Z
      58: ifne          65
      61: iconst_1
      62: goto          66
      65: iconst_0
      66: istore        7
      68: aload_1
      69: aload         6
      71: if_acmpeq     217
      74: aload_1
      75: invokevirtual #474                // Method net/minecraft/world/entity/LivingEntity.getTeam:()Lnet/minecraft/world/scores/PlayerTeam;
      78: astore        8
      80: aload         6
      82: invokevirtual #475                // Method net/minecraft/client/player/LocalPlayer.getTeam:()Lnet/minecraft/world/scores/PlayerTeam;
      85: astore        9
      87: aload         8
      89: ifnull        217
      92: aload         8
      94: invokevirtual #479                // Method net/minecraft/world/scores/Team.getNameTagVisibility:()Lnet/minecraft/world/scores/Team$Visibility;
      97: astore        10
      99: getstatic     #482                // Field net/minecraft/client/renderer/entity/LivingEntityRenderer$1.$SwitchMap$net$minecraft$world$scores$Team$Visibility:[I
     102: aload         10
     104: invokevirtual #483                // Method net/minecraft/world/scores/Team$Visibility.ordinal:()I
     107: iaload
     108: tableswitch   { // 1 to 4
                     1: 140
                     2: 143
                     3: 145
                     4: 184
               default: 215
          }
     140: iload         7
     142: ireturn
     143: iconst_0
     144: ireturn
     145: aload         9
     147: ifnonnull     155
     150: iload         7
     152: goto          183
     155: aload         8
     157: aload         9
     159: invokevirtual #489                // Method net/minecraft/world/scores/Team.isAlliedTo:(Lnet/minecraft/world/scores/Team;)Z
     162: ifeq          182
     165: aload         8
     167: invokevirtual #492                // Method net/minecraft/world/scores/Team.canSeeFriendlyInvisibles:()Z
     170: ifne          178
     173: iload         7
     175: ifeq          182
     178: iconst_1
     179: goto          183
     182: iconst_0
     183: ireturn
     184: aload         9
     186: ifnonnull     194
     189: iload         7
     191: goto          214
     194: aload         8
     196: aload         9
     198: invokevirtual #489                // Method net/minecraft/world/scores/Team.isAlliedTo:(Lnet/minecraft/world/scores/Team;)Z
     201: ifne          213
     204: iload         7
     206: ifeq          213
     209: iconst_1
     210: goto          214
     213: iconst_0
     214: ireturn
     215: iconst_1
     216: ireturn
     217: invokestatic  #495                // Method net/minecraft/client/Minecraft.renderNames:()Z
     220: ifeq          248
     223: aload_1
     224: aload         5
     226: invokevirtual #498                // Method net/minecraft/client/Minecraft.getCameraEntity:()Lnet/minecraft/world/entity/Entity;
     229: if_acmpeq     248
     232: iload         7
     234: ifeq          248
     237: aload_1
     238: invokevirtual #501                // Method net/minecraft/world/entity/LivingEntity.isVehicle:()Z
     241: ifne          248
     244: iconst_1
     245: goto          249
     248: iconst_0
     249: ireturn

  public static boolean isEntityUpsideDown(net.minecraft.world.entity.LivingEntity);
    Code:
       0: aload_0
       1: instanceof    #511                // class net/minecraft/world/entity/player/Player
       4: ifne          14
       7: aload_0
       8: invokevirtual #514                // Method net/minecraft/world/entity/LivingEntity.hasCustomName:()Z
      11: ifeq          73
      14: aload_0
      15: invokevirtual #518                // Method net/minecraft/world/entity/LivingEntity.getName:()Lnet/minecraft/network/chat/Component;
      18: invokeinterface #524,  1          // InterfaceMethod net/minecraft/network/chat/Component.getString:()Ljava/lang/String;
      23: invokestatic  #530                // Method net/minecraft/ChatFormatting.stripFormatting:(Ljava/lang/String;)Ljava/lang/String;
      26: astore_1
      27: ldc_w         #532                // String Dinnerbone
      30: aload_1
      31: invokevirtual #537                // Method java/lang/String.equals:(Ljava/lang/Object;)Z
      34: ifne          47
      37: ldc_w         #539                // String Grumm
      40: aload_1
      41: invokevirtual #537                // Method java/lang/String.equals:(Ljava/lang/Object;)Z
      44: ifeq          73
      47: aload_0
      48: instanceof    #511                // class net/minecraft/world/entity/player/Player
      51: ifeq          67
      54: aload_0
      55: checkcast     #511                // class net/minecraft/world/entity/player/Player
      58: getstatic     #545                // Field net/minecraft/world/entity/player/PlayerModelPart.CAPE:Lnet/minecraft/world/entity/player/PlayerModelPart;
      61: invokevirtual #549                // Method net/minecraft/world/entity/player/Player.isModelPartShown:(Lnet/minecraft/world/entity/player/PlayerModelPart;)Z
      64: ifeq          71
      67: iconst_1
      68: goto          72
      71: iconst_0
      72: ireturn
      73: iconst_0
      74: ireturn

  protected float getShadowRadius(T);
    Code:
       0: aload_0
       1: aload_1
       2: invokespecial #555                // Method net/minecraft/client/renderer/entity/EntityRenderer.getShadowRadius:(Lnet/minecraft/world/entity/Entity;)F
       5: aload_1
       6: invokevirtual #195                // Method net/minecraft/world/entity/LivingEntity.getScale:()F
       9: fmul
      10: freturn

  protected float getShadowRadius(net.minecraft.world.entity.Entity);
    Code:
       0: aload_0
       1: aload_1
       2: checkcast     #97                 // class net/minecraft/world/entity/LivingEntity
       5: invokevirtual #558                // Method getShadowRadius:(Lnet/minecraft/world/entity/LivingEntity;)F
       8: freturn

  protected boolean shouldShowName(net.minecraft.world.entity.Entity);
    Code:
       0: aload_0
       1: aload_1
       2: checkcast     #97                 // class net/minecraft/world/entity/LivingEntity
       5: invokevirtual #561                // Method shouldShowName:(Lnet/minecraft/world/entity/LivingEntity;)Z
       8: ireturn

  public void render(net.minecraft.world.entity.Entity, float, float, com.mojang.blaze3d.vertex.PoseStack, net.minecraft.client.renderer.MultiBufferSource, int);
    Code:
       0: aload_0
       1: aload_1
       2: checkcast     #97                 // class net/minecraft/world/entity/LivingEntity
       5: fload_2
       6: fload_3
       7: aload         4
       9: aload         5
      11: iload         6
      13: invokevirtual #563                // Method render:(Lnet/minecraft/world/entity/LivingEntity;FFLcom/mojang/blaze3d/vertex/PoseStack;Lnet/minecraft/client/renderer/MultiBufferSource;I)V
      16: return

  static {};
    Code:
       0: invokestatic  #570                // Method com/mojang/logging/LogUtils.getLogger:()Lorg/slf4j/Logger;
       3: putstatic     #572                // Field LOGGER:Lorg/slf4j/Logger;
       6: return
}
