Compiled from "ManagedConfig.kt"
public final class io.github.notenoughupdates.moulconfig.managed.ManagedConfig<T extends io.github.notenoughupdates.moulconfig.Config> extends io.github.notenoughupdates.moulconfig.managed.ManagedDataFile<T> {
  public static final io.github.notenoughupdates.moulconfig.managed.ManagedConfig$Companion Companion;

  private final io.github.notenoughupdates.moulconfig.managed.ManagedConfigBuilder<T> builder;

  private io.github.notenoughupdates.moulconfig.processor.MoulConfigProcessor<T> processor;

  public io.github.notenoughupdates.moulconfig.managed.ManagedConfig(io.github.notenoughupdates.moulconfig.managed.ManagedConfigBuilder<T>);
    Code:
       0: aload_1
       1: ldc           #58                 // String builder
       3: invokestatic  #64                 // Method kotlin/jvm/internal/Intrinsics.checkNotNullParameter:(Ljava/lang/Object;Ljava/lang/String;)V
       6: aload_0
       7: aload_1
       8: astore_2
       9: aload_2
      10: astore_3
      11: astore        5
      13: iconst_0
      14: istore        4
      16: aload_3
      17: aload_1
      18: invokedynamic #84,  0             // InvokeDynamic #0:accept:(Lio/github/notenoughupdates/moulconfig/managed/ManagedConfigBuilder;)Ljava/util/function/Consumer;
      23: aload_3
      24: invokevirtual #90                 // Method io/github/notenoughupdates/moulconfig/managed/ManagedConfigBuilder.getAfterLoad:()Ljava/util/function/Consumer;
      27: invokeinterface #96,  2           // InterfaceMethod java/util/function/Consumer.andThen:(Ljava/util/function/Consumer;)Ljava/util/function/Consumer;
      32: invokevirtual #100                // Method io/github/notenoughupdates/moulconfig/managed/ManagedConfigBuilder.setAfterLoad:(Ljava/util/function/Consumer;)V
      35: nop
      36: aload         5
      38: aload_2
      39: checkcast     #102                // class io/github/notenoughupdates/moulconfig/managed/ManagedDataFileBuilder
      42: invokespecial #105                // Method io/github/notenoughupdates/moulconfig/managed/ManagedDataFile."<init>":(Lio/github/notenoughupdates/moulconfig/managed/ManagedDataFileBuilder;)V
      45: aload_0
      46: aload_1
      47: putfield      #107                // Field builder:Lio/github/notenoughupdates/moulconfig/managed/ManagedConfigBuilder;
      50: return

  public final io.github.notenoughupdates.moulconfig.processor.MoulConfigProcessor<T> getProcessor();
    Code:
       0: aload_0
       1: getfield      #114                // Field processor:Lio/github/notenoughupdates/moulconfig/processor/MoulConfigProcessor;
       4: dup
       5: ifnull        9
       8: areturn
       9: pop
      10: ldc           #117                // String processor
      12: invokestatic  #121                // Method kotlin/jvm/internal/Intrinsics.throwUninitializedPropertyAccessException:(Ljava/lang/String;)V
      15: aconst_null
      16: areturn

  public void injectIntoInstance();
    Code:
       0: aload_0
       1: invokevirtual #125                // Method getInstance:()Ljava/lang/Object;
       4: checkcast     #127                // class io/github/notenoughupdates/moulconfig/Config
       7: getfield      #131                // Field io/github/notenoughupdates/moulconfig/Config.saveRunnables:Ljava/util/List;
      10: dup
      11: ifnull        29
      14: aload_0
      15: invokedynamic #140,  0            // InvokeDynamic #1:run:(Lio/github/notenoughupdates/moulconfig/managed/ManagedConfig;)Ljava/lang/Runnable;
      20: invokeinterface #146,  2          // InterfaceMethod java/util/List.add:(Ljava/lang/Object;)Z
      25: pop
      26: goto          30
      29: pop
      30: return

  public final void rebuildConfigProcessor();
    Code:
       0: aload_0
       1: aload_0
       2: getfield      #107                // Field builder:Lio/github/notenoughupdates/moulconfig/managed/ManagedConfigBuilder;
       5: invokespecial #148                // Method rebuildConfigProcessor:(Lio/github/notenoughupdates/moulconfig/managed/ManagedConfigBuilder;)V
       8: return

  private final void rebuildConfigProcessor(io.github.notenoughupdates.moulconfig.managed.ManagedConfigBuilder<T>);
    Code:
       0: aload_0
       1: aload_0
       2: aload_1
       3: invokespecial #150                // Method buildProcessor:(Lio/github/notenoughupdates/moulconfig/managed/ManagedConfigBuilder;)Lio/github/notenoughupdates/moulconfig/processor/MoulConfigProcessor;
       6: putfield      #114                // Field processor:Lio/github/notenoughupdates/moulconfig/processor/MoulConfigProcessor;
       9: return

  private final <A extends java.lang.annotation.Annotation> void cast(io.github.notenoughupdates.moulconfig.processor.MoulConfigProcessor<T>, java.lang.Class<A>, java.lang.Object);
    Code:
       0: iconst_0
       1: istore        4
       3: aload_1
       4: aload_2
       5: aload_3
       6: ldc           #153                // String null cannot be cast to non-null type java.util.function.BiFunction<io.github.notenoughupdates.moulconfig.processor.ProcessedOption, A of io.github.notenoughupdates.moulconfig.managed.ManagedConfig.cast, io.github.notenoughupdates.moulconfig.gui.GuiOptionEditor>
       8: invokestatic  #156                // Method kotlin/jvm/internal/Intrinsics.checkNotNull:(Ljava/lang/Object;Ljava/lang/String;)V
      11: aload_3
      12: checkcast     #158                // class java/util/function/BiFunction
      15: invokevirtual #162                // Method io/github/notenoughupdates/moulconfig/processor/MoulConfigProcessor.registerConfigEditor:(Ljava/lang/Class;Ljava/util/function/BiFunction;)V
      18: return

  private final io.github.notenoughupdates.moulconfig.processor.MoulConfigProcessor<T> buildProcessor(io.github.notenoughupdates.moulconfig.managed.ManagedConfigBuilder<T>);
    Code:
       0: new           #116                // class io/github/notenoughupdates/moulconfig/processor/MoulConfigProcessor
       3: dup
       4: aload_0
       5: invokevirtual #125                // Method getInstance:()Ljava/lang/Object;
       8: checkcast     #127                // class io/github/notenoughupdates/moulconfig/Config
      11: invokespecial #168                // Method io/github/notenoughupdates/moulconfig/processor/MoulConfigProcessor."<init>":(Lio/github/notenoughupdates/moulconfig/Config;)V
      14: astore_2
      15: aload_1
      16: invokevirtual #172                // Method io/github/notenoughupdates/moulconfig/managed/ManagedConfigBuilder.getUseDefaultProcessors:()Z
      19: ifeq          26
      22: aload_2
      23: invokestatic  #178                // Method io/github/notenoughupdates/moulconfig/processor/BuiltinMoulConfigGuis.addProcessors:(Lio/github/notenoughupdates/moulconfig/processor/MoulConfigProcessor;)V
      26: aload_1
      27: invokevirtual #182                // Method io/github/notenoughupdates/moulconfig/managed/ManagedConfigBuilder.getCustomProcessors$common:()Ljava/util/List;
      30: checkcast     #184                // class java/lang/Iterable
      33: astore_3
      34: iconst_0
      35: istore        4
      37: aload_3
      38: invokeinterface #188,  1          // InterfaceMethod java/lang/Iterable.iterator:()Ljava/util/Iterator;
      43: astore        5
      45: aload         5
      47: invokeinterface #193,  1          // InterfaceMethod java/util/Iterator.hasNext:()Z
      52: ifeq          121
      55: aload         5
      57: invokeinterface #196,  1          // InterfaceMethod java/util/Iterator.next:()Ljava/lang/Object;
      62: astore        6
      64: aload         6
      66: checkcast     #198                // class kotlin/Pair
      69: astore        7
      71: iconst_0
      72: istore        8
      74: aload         7
      76: invokevirtual #201                // Method kotlin/Pair.component1:()Ljava/lang/Object;
      79: checkcast     #203                // class java/lang/Class
      82: astore        9
      84: aload         7
      86: invokevirtual #206                // Method kotlin/Pair.component2:()Ljava/lang/Object;
      89: checkcast     #158                // class java/util/function/BiFunction
      92: astore        10
      94: aload_0
      95: astore        11
      97: iconst_0
      98: istore        12
     100: aload_2
     101: aload         9
     103: aload         10
     105: ldc           #153                // String null cannot be cast to non-null type java.util.function.BiFunction<io.github.notenoughupdates.moulconfig.processor.ProcessedOption, A of io.github.notenoughupdates.moulconfig.managed.ManagedConfig.cast, io.github.notenoughupdates.moulconfig.gui.GuiOptionEditor>
     107: invokestatic  #156                // Method kotlin/jvm/internal/Intrinsics.checkNotNull:(Ljava/lang/Object;Ljava/lang/String;)V
     110: aload         10
     112: invokevirtual #162                // Method io/github/notenoughupdates/moulconfig/processor/MoulConfigProcessor.registerConfigEditor:(Ljava/lang/Class;Ljava/util/function/BiFunction;)V
     115: nop
     116: nop
     117: nop
     118: goto          45
     121: nop
     122: new           #208                // class io/github/notenoughupdates/moulconfig/processor/ConfigProcessorDriver
     125: dup
     126: aload_2
     127: checkcast     #210                // class io/github/notenoughupdates/moulconfig/processor/ConfigStructureReader
     130: invokespecial #213                // Method io/github/notenoughupdates/moulconfig/processor/ConfigProcessorDriver."<init>":(Lio/github/notenoughupdates/moulconfig/processor/ConfigStructureReader;)V
     133: astore_3
     134: aload_3
     135: aload_1
     136: invokevirtual #216                // Method io/github/notenoughupdates/moulconfig/managed/ManagedConfigBuilder.getCheckExpose:()Z
     139: putfield      #220                // Field io/github/notenoughupdates/moulconfig/processor/ConfigProcessorDriver.checkExpose:Z
     142: aload_3
     143: aload_0
     144: invokevirtual #125                // Method getInstance:()Ljava/lang/Object;
     147: checkcast     #127                // class io/github/notenoughupdates/moulconfig/Config
     150: invokevirtual #223                // Method io/github/notenoughupdates/moulconfig/processor/ConfigProcessorDriver.processConfig:(Lio/github/notenoughupdates/moulconfig/Config;)V
     153: aload_2
     154: areturn

  public final io.github.notenoughupdates.moulconfig.gui.MoulConfigEditor<T> getEditor();
    Code:
       0: new           #235                // class io/github/notenoughupdates/moulconfig/gui/MoulConfigEditor
       3: dup
       4: aload_0
       5: invokevirtual #237                // Method getProcessor:()Lio/github/notenoughupdates/moulconfig/processor/MoulConfigProcessor;
       8: invokespecial #239                // Method io/github/notenoughupdates/moulconfig/gui/MoulConfigEditor."<init>":(Lio/github/notenoughupdates/moulconfig/processor/MoulConfigProcessor;)V
      11: areturn

  public final void openConfigGui();
    Code:
       0: getstatic     #245                // Field io/github/notenoughupdates/moulconfig/common/IMinecraft.INSTANCE:Lio/github/notenoughupdates/moulconfig/common/IMinecraft;
       3: aload_0
       4: invokevirtual #247                // Method getEditor:()Lio/github/notenoughupdates/moulconfig/gui/MoulConfigEditor;
       7: checkcast     #249                // class io/github/notenoughupdates/moulconfig/gui/GuiElement
      10: invokeinterface #253,  2          // InterfaceMethod io/github/notenoughupdates/moulconfig/common/IMinecraft.openWrappedScreen:(Lio/github/notenoughupdates/moulconfig/gui/GuiElement;)V
      15: return

  private static final void _init_$lambda$1$lambda$0(io.github.notenoughupdates.moulconfig.managed.ManagedConfigBuilder, io.github.notenoughupdates.moulconfig.managed.ManagedDataFile);
    Code:
       0: aload_1
       1: ldc           #255                // String null cannot be cast to non-null type io.github.notenoughupdates.moulconfig.managed.ManagedConfig<T of io.github.notenoughupdates.moulconfig.managed.ManagedConfig>
       3: invokestatic  #156                // Method kotlin/jvm/internal/Intrinsics.checkNotNull:(Ljava/lang/Object;Ljava/lang/String;)V
       6: aload_1
       7: checkcast     #2                  // class io/github/notenoughupdates/moulconfig/managed/ManagedConfig
      10: aload_0
      11: invokespecial #148                // Method rebuildConfigProcessor:(Lio/github/notenoughupdates/moulconfig/managed/ManagedConfigBuilder;)V
      14: return

  public static final <T extends io.github.notenoughupdates.moulconfig.Config> io.github.notenoughupdates.moulconfig.managed.ManagedConfig<T> create(java.io.File, java.lang.Class<T>, kotlin.jvm.functions.Function1<? super io.github.notenoughupdates.moulconfig.managed.ManagedConfigBuilder<T>, kotlin.Unit>);
    Code:
       0: getstatic     #264                // Field Companion:Lio/github/notenoughupdates/moulconfig/managed/ManagedConfig$Companion;
       3: aload_0
       4: aload_1
       5: aload_2
       6: invokevirtual #266                // Method io/github/notenoughupdates/moulconfig/managed/ManagedConfig$Companion.create:(Ljava/io/File;Ljava/lang/Class;Lkotlin/jvm/functions/Function1;)Lio/github/notenoughupdates/moulconfig/managed/ManagedConfig;
       9: areturn

  public static final <T extends io.github.notenoughupdates.moulconfig.Config> io.github.notenoughupdates.moulconfig.managed.ManagedConfig<T> create(java.io.File, java.lang.Class<T>);
    Code:
       0: getstatic     #264                // Field Companion:Lio/github/notenoughupdates/moulconfig/managed/ManagedConfig$Companion;
       3: aload_0
       4: aload_1
       5: invokevirtual #275                // Method io/github/notenoughupdates/moulconfig/managed/ManagedConfig$Companion.create:(Ljava/io/File;Ljava/lang/Class;)Lio/github/notenoughupdates/moulconfig/managed/ManagedConfig;
       8: areturn

  static {};
    Code:
       0: new           #52                 // class io/github/notenoughupdates/moulconfig/managed/ManagedConfig$Companion
       3: dup
       4: aconst_null
       5: invokespecial #279                // Method io/github/notenoughupdates/moulconfig/managed/ManagedConfig$Companion."<init>":(Lkotlin/jvm/internal/DefaultConstructorMarker;)V
       8: putstatic     #264                // Field Companion:Lio/github/notenoughupdates/moulconfig/managed/ManagedConfig$Companion;
      11: return
}
