Compiled from "MoulConfigPlatform.java"
public class io.github.notenoughupdates.moulconfig.platform.MoulConfigPlatform implements io.github.notenoughupdates.moulconfig.common.IMinecraft {
  private static final org.slf4j.Logger log;

  public static io.github.notenoughupdates.moulconfig.platform.MoulConfigPlatform instance;

  net.minecraft.class_310 mc;

  static final boolean $assertionsDisabled;

  public io.github.notenoughupdates.moulconfig.platform.MoulConfigPlatform();
    Code:
       0: aload_0
       1: invokespecial #60                 // Method java/lang/Object."<init>":()V
       4: aload_0
       5: invokestatic  #66                 // Method net/minecraft/class_310.method_1551:()Lnet/minecraft/class_310;
       8: putfield      #68                 // Field mc:Lnet/minecraft/class_310;
      11: getstatic     #70                 // Field instance:Lio/github/notenoughupdates/moulconfig/platform/MoulConfigPlatform;
      14: ifnull        22
      17: ldc           #72                 // String Constructed duplicate MoulConfig instance
      19: invokestatic  #78                 // Method io/github/notenoughupdates/moulconfig/internal/Warnings.warn:(Ljava/lang/String;)V
      22: aload_0
      23: putstatic     #70                 // Field instance:Lio/github/notenoughupdates/moulconfig/platform/MoulConfigPlatform;
      26: return

  public static net.minecraft.class_2960 unwrap(io.github.notenoughupdates.moulconfig.common.MyResourceLocation);
    Code:
       0: aload_0
       1: invokevirtual #87                 // Method io/github/notenoughupdates/moulconfig/common/MyResourceLocation.getRoot:()Ljava/lang/String;
       4: aload_0
       5: invokevirtual #90                 // Method io/github/notenoughupdates/moulconfig/common/MyResourceLocation.getPath:()Ljava/lang/String;
       8: invokestatic  #96                 // Method net/minecraft/class_2960.method_60655:(Ljava/lang/String;Ljava/lang/String;)Lnet/minecraft/class_2960;
      11: areturn

  public static io.github.notenoughupdates.moulconfig.common.MyResourceLocation wrap(net.minecraft.class_2960);
    Code:
       0: new           #83                 // class io/github/notenoughupdates/moulconfig/common/MyResourceLocation
       3: dup
       4: aload_0
       5: invokevirtual #103                // Method net/minecraft/class_2960.method_12836:()Ljava/lang/String;
       8: aload_0
       9: invokevirtual #106                // Method net/minecraft/class_2960.method_12832:()Ljava/lang/String;
      12: invokespecial #109                // Method io/github/notenoughupdates/moulconfig/common/MyResourceLocation."<init>":(Ljava/lang/String;Ljava/lang/String;)V
      15: areturn

  public static net.minecraft.class_1799 unwrap(io.github.notenoughupdates.moulconfig.common.IItemStack);
    Code:
       0: aload_0
       1: checkcast     #114                // class io/github/notenoughupdates/moulconfig/platform/MoulConfigItemStack
       4: invokevirtual #118                // Method io/github/notenoughupdates/moulconfig/platform/MoulConfigItemStack.getItemStack:()Lnet/minecraft/class_1799;
       7: areturn

  public static io.github.notenoughupdates.moulconfig.common.IItemStack wrap(net.minecraft.class_1799);
    Code:
       0: new           #114                // class io/github/notenoughupdates/moulconfig/platform/MoulConfigItemStack
       3: dup
       4: aload_0
       5: invokespecial #124                // Method io/github/notenoughupdates/moulconfig/platform/MoulConfigItemStack."<init>":(Lnet/minecraft/class_1799;)V
       8: areturn

  public static net.minecraft.class_2561 unwrap(io.github.notenoughupdates.moulconfig.common.text.StructuredText);
    Code:
       0: aload_0
       1: invokestatic  #130                // Method io/github/notenoughupdates/moulconfig/platform/MoulConfigText.unwrap:(Lio/github/notenoughupdates/moulconfig/common/text/StructuredText;)Lnet/minecraft/class_2561;
       4: areturn

  public static io.github.notenoughupdates.moulconfig.common.text.StructuredText wrap(net.minecraft.class_2561);
    Code:
       0: aload_0
       1: invokestatic  #135                // Method io/github/notenoughupdates/moulconfig/platform/MoulConfigText.wrap:(Lnet/minecraft/class_2561;)Lio/github/notenoughupdates/moulconfig/common/text/StructuredText;
       4: areturn

  public static io.github.notenoughupdates.moulconfig.common.text.StructuredText$Mutable wrap(net.minecraft.class_5250);
    Code:
       0: aload_0
       1: invokestatic  #140                // Method io/github/notenoughupdates/moulconfig/platform/MoulConfigText.wrap:(Lnet/minecraft/class_5250;)Lio/github/notenoughupdates/moulconfig/common/text/StructuredText$Mutable;
       4: areturn

  public static net.minecraft.class_327 unwrap(io.github.notenoughupdates.moulconfig.common.IFontRenderer);
    Code:
       0: aload_0
       1: checkcast     #144                // class io/github/notenoughupdates/moulconfig/platform/MoulConfigFontRenderer
       4: invokevirtual #148                // Method io/github/notenoughupdates/moulconfig/platform/MoulConfigFontRenderer.getFont:()Lnet/minecraft/class_327;
       7: areturn

  public static io.github.notenoughupdates.moulconfig.common.IFontRenderer wrap(net.minecraft.class_327);
    Code:
       0: new           #144                // class io/github/notenoughupdates/moulconfig/platform/MoulConfigFontRenderer
       3: dup
       4: aload_0
       5: invokespecial #154                // Method io/github/notenoughupdates/moulconfig/platform/MoulConfigFontRenderer."<init>":(Lnet/minecraft/class_327;)V
       8: areturn

  public java.io.InputStream loadResourceLocation(io.github.notenoughupdates.moulconfig.common.MyResourceLocation);
    Code:
       0: aload_0
       1: getfield      #68                 // Field mc:Lnet/minecraft/class_310;
       4: invokevirtual #164                // Method net/minecraft/class_310.method_1478:()Lnet/minecraft/class_3300;
       7: aload_1
       8: invokestatic  #166                // Method unwrap:(Lio/github/notenoughupdates/moulconfig/common/MyResourceLocation;)Lnet/minecraft/class_2960;
      11: invokeinterface #172,  2          // InterfaceMethod net/minecraft/class_3300.getResourceOrThrow:(Lnet/minecraft/class_2960;)Lnet/minecraft/class_3298;
      16: invokevirtual #178                // Method net/minecraft/class_3298.method_14482:()Ljava/io/InputStream;
      19: areturn
      20: astore_2
      21: aload_2
      22: athrow
    Exception table:
       from    to  target type
           0    19    20   Class java/lang/Throwable

  public io.github.notenoughupdates.moulconfig.internal.MCLogger getLogger(java.lang.String);
    Code:
       0: aload_1
       1: invokestatic  #187                // Method org/apache/logging/log4j/LogManager.getLogger:(Ljava/lang/String;)Lorg/apache/logging/log4j/Logger;
       4: astore_2
       5: new           #14                 // class io/github/notenoughupdates/moulconfig/platform/MoulConfigPlatform$1
       8: dup
       9: aload_0
      10: aload_2
      11: invokespecial #190                // Method io/github/notenoughupdates/moulconfig/platform/MoulConfigPlatform$1."<init>":(Lio/github/notenoughupdates/moulconfig/platform/MoulConfigPlatform;Lorg/apache/logging/log4j/Logger;)V
      14: areturn

  public boolean isGeneratedSentinel(io.github.notenoughupdates.moulconfig.common.MyResourceLocation);
    Code:
       0: ldc           #198                // String moulconfig
       2: aload_1
       3: invokevirtual #87                 // Method io/github/notenoughupdates/moulconfig/common/MyResourceLocation.getRoot:()Ljava/lang/String;
       6: invokestatic  #204                // Method java/util/Objects.equals:(Ljava/lang/Object;Ljava/lang/Object;)Z
       9: ifeq          28
      12: aload_1
      13: invokevirtual #90                 // Method io/github/notenoughupdates/moulconfig/common/MyResourceLocation.getPath:()Ljava/lang/String;
      16: ldc           #206                // String dynamic/
      18: invokevirtual #212                // Method java/lang/String.startsWith:(Ljava/lang/String;)Z
      21: ifeq          28
      24: iconst_1
      25: goto          29
      28: iconst_0
      29: ireturn

  private static void setTextureData(net.minecraft.class_1043, java.awt.image.BufferedImage);
    Code:
       0: aload_0
       1: invokevirtual #220                // Method net/minecraft/class_1043.method_4525:()Lnet/minecraft/class_1011;
       4: astore_2
       5: getstatic     #222                // Field $assertionsDisabled:Z
       8: ifne          23
      11: aload_2
      12: ifnonnull     23
      15: new           #224                // class java/lang/AssertionError
      18: dup
      19: invokespecial #225                // Method java/lang/AssertionError."<init>":()V
      22: athrow
      23: iconst_0
      24: istore_3
      25: iload_3
      26: aload_1
      27: invokevirtual #233                // Method java/awt/image/BufferedImage.getWidth:()I
      30: if_icmpge     75
      33: iconst_0
      34: istore        4
      36: iload         4
      38: aload_1
      39: invokevirtual #236                // Method java/awt/image/BufferedImage.getHeight:()I
      42: if_icmpge     69
      45: aload_1
      46: iload_3
      47: iload         4
      49: invokevirtual #240                // Method java/awt/image/BufferedImage.getRGB:(II)I
      52: istore        5
      54: aload_2
      55: iload_3
      56: iload         4
      58: iload         5
      60: invokevirtual #244                // Method net/minecraft/class_1011.method_61941:(III)V
      63: iinc          4, 1
      66: goto          36
      69: iinc          3, 1
      72: goto          25
      75: return

  public io.github.notenoughupdates.moulconfig.common.DynamicTextureReference generateDynamicTexture(java.awt.image.BufferedImage);
    Code:
       0: ldc           #198                // String moulconfig
       2: invokestatic  #262                // Method java/util/concurrent/ThreadLocalRandom.current:()Ljava/util/concurrent/ThreadLocalRandom;
       5: invokevirtual #266                // Method java/util/concurrent/ThreadLocalRandom.nextLong:()J
       8: invokedynamic #278,  0            // InvokeDynamic #0:makeConcatWithConstants:(J)Ljava/lang/String;
      13: invokestatic  #96                 // Method net/minecraft/class_2960.method_60655:(Ljava/lang/String;Ljava/lang/String;)Lnet/minecraft/class_2960;
      16: astore_2
      17: new           #216                // class net/minecraft/class_1043
      20: dup
      21: aload_2
      22: invokevirtual #106                // Method net/minecraft/class_2960.method_12832:()Ljava/lang/String;
      25: aload_1
      26: invokevirtual #233                // Method java/awt/image/BufferedImage.getWidth:()I
      29: aload_1
      30: invokevirtual #236                // Method java/awt/image/BufferedImage.getHeight:()I
      33: iconst_1
      34: invokespecial #281                // Method net/minecraft/class_1043."<init>":(Ljava/lang/String;IIZ)V
      37: astore_3
      38: aload_3
      39: aload_1
      40: invokestatic  #283                // Method setTextureData:(Lnet/minecraft/class_1043;Ljava/awt/image/BufferedImage;)V
      43: aload_3
      44: invokevirtual #286                // Method net/minecraft/class_1043.method_4524:()V
      47: aload_0
      48: getfield      #68                 // Field mc:Lnet/minecraft/class_310;
      51: invokevirtual #290                // Method net/minecraft/class_310.method_1531:()Lnet/minecraft/class_1060;
      54: aload_2
      55: aload_3
      56: invokevirtual #296                // Method net/minecraft/class_1060.method_4616:(Lnet/minecraft/class_2960;Lnet/minecraft/class_1044;)V
      59: new           #12                 // class io/github/notenoughupdates/moulconfig/platform/MoulConfigPlatform$2
      62: dup
      63: aload_0
      64: aload_2
      65: aload_3
      66: invokespecial #299                // Method io/github/notenoughupdates/moulconfig/platform/MoulConfigPlatform$2."<init>":(Lio/github/notenoughupdates/moulconfig/platform/MoulConfigPlatform;Lnet/minecraft/class_2960;Lnet/minecraft/class_1043;)V
      69: areturn

  public kotlin.Pair<java.lang.Double, java.lang.Double> getMousePositionHF();
    Code:
       0: aload_0
       1: getfield      #68                 // Field mc:Lnet/minecraft/class_310;
       4: getfield      #307                // Field net/minecraft/class_310.field_1729:Lnet/minecraft/class_312;
       7: astore_1
       8: aload_0
       9: getfield      #68                 // Field mc:Lnet/minecraft/class_310;
      12: invokevirtual #311                // Method net/minecraft/class_310.method_22683:()Lnet/minecraft/class_1041;
      15: astore_2
      16: aload_1
      17: aload_2
      18: invokevirtual #317                // Method net/minecraft/class_312.method_68879:(Lnet/minecraft/class_1041;)D
      21: dstore_3
      22: aload_1
      23: aload_2
      24: invokevirtual #320                // Method net/minecraft/class_312.method_68883:(Lnet/minecraft/class_1041;)D
      27: dstore        5
      29: new           #322                // class kotlin/Pair
      32: dup
      33: dload_3
      34: invokestatic  #328                // Method java/lang/Double.valueOf:(D)Ljava/lang/Double;
      37: dload         5
      39: invokestatic  #328                // Method java/lang/Double.valueOf:(D)Ljava/lang/Double;
      42: invokespecial #331                // Method kotlin/Pair."<init>":(Ljava/lang/Object;Ljava/lang/Object;)V
      45: areturn

  public boolean isDevelopmentEnvironment();
    Code:
       0: invokestatic  #345                // InterfaceMethod net/fabricmc/loader/api/FabricLoader.getInstance:()Lnet/fabricmc/loader/api/FabricLoader;
       3: invokeinterface #347,  1          // InterfaceMethod net/fabricmc/loader/api/FabricLoader.isDevelopmentEnvironment:()Z
       8: ireturn

  public io.github.notenoughupdates.moulconfig.common.IFontRenderer getDefaultFontRenderer();
    Code:
       0: new           #144                // class io/github/notenoughupdates/moulconfig/platform/MoulConfigFontRenderer
       3: dup
       4: aload_0
       5: getfield      #68                 // Field mc:Lnet/minecraft/class_310;
       8: getfield      #352                // Field net/minecraft/class_310.field_1772:Lnet/minecraft/class_327;
      11: invokespecial #154                // Method io/github/notenoughupdates/moulconfig/platform/MoulConfigFontRenderer."<init>":(Lnet/minecraft/class_327;)V
      14: areturn

  public io.github.notenoughupdates.moulconfig.common.IKeyboardConstants getKeyboardConstants();
    Code:
       0: getstatic     #360                // Field io/github/notenoughupdates/moulconfig/platform/ModernKeyboardConstants.INSTANCE:Lio/github/notenoughupdates/moulconfig/platform/ModernKeyboardConstants;
       3: areturn

  public int getScaledWidth();
    Code:
       0: aload_0
       1: getfield      #68                 // Field mc:Lnet/minecraft/class_310;
       4: invokevirtual #311                // Method net/minecraft/class_310.method_22683:()Lnet/minecraft/class_1041;
       7: invokevirtual #366                // Method net/minecraft/class_1041.method_4486:()I
      10: ireturn

  public int getScaledHeight();
    Code:
       0: aload_0
       1: getfield      #68                 // Field mc:Lnet/minecraft/class_310;
       4: invokevirtual #311                // Method net/minecraft/class_310.method_22683:()Lnet/minecraft/class_1041;
       7: invokevirtual #370                // Method net/minecraft/class_1041.method_4502:()I
      10: ireturn

  public int getScaleFactor();
    Code:
       0: aload_0
       1: getfield      #68                 // Field mc:Lnet/minecraft/class_310;
       4: invokevirtual #311                // Method net/minecraft/class_310.method_22683:()Lnet/minecraft/class_1041;
       7: invokevirtual #374                // Method net/minecraft/class_1041.method_4495:()I
      10: ireturn

  public boolean isOnMacOs();
    Code:
       0: invokestatic  #379                // Method net/minecraft/class_156.method_668:()Lnet/minecraft/class_156$class_158;
       3: getstatic     #383                // Field net/minecraft/class_156$class_158.field_1137:Lnet/minecraft/class_156$class_158;
       6: if_acmpne     13
       9: iconst_1
      10: goto          14
      13: iconst_0
      14: ireturn

  public boolean isMouseButtonDown(int);
    Code:
       0: aload_0
       1: getfield      #68                 // Field mc:Lnet/minecraft/class_310;
       4: invokevirtual #311                // Method net/minecraft/class_310.method_22683:()Lnet/minecraft/class_1041;
       7: invokevirtual #388                // Method net/minecraft/class_1041.method_4490:()J
      10: iload_1
      11: invokestatic  #394                // Method org/lwjgl/glfw/GLFW.glfwGetMouseButton:(JI)I
      14: iconst_1
      15: if_icmpne     22
      18: iconst_1
      19: goto          23
      22: iconst_0
      23: ireturn

  public boolean isKeyboardKeyDown(int);
    Code:
       0: aload_0
       1: getfield      #68                 // Field mc:Lnet/minecraft/class_310;
       4: invokevirtual #311                // Method net/minecraft/class_310.method_22683:()Lnet/minecraft/class_1041;
       7: iload_1
       8: invokestatic  #402                // Method net/minecraft/class_3675.method_15987:(Lnet/minecraft/class_1041;I)Z
      11: ireturn

  public void addExtraBuiltinConfigProcessors(io.github.notenoughupdates.moulconfig.processor.MoulConfigProcessor<?>);
    Code:
       0: return

  public void sendClickableChatMessage(io.github.notenoughupdates.moulconfig.common.text.StructuredText, java.lang.String, io.github.notenoughupdates.moulconfig.common.ClickType);
    Code:
       0: aload_1
       1: invokestatic  #130                // Method io/github/notenoughupdates/moulconfig/platform/MoulConfigText.unwrap:(Lio/github/notenoughupdates/moulconfig/common/text/StructuredText;)Lnet/minecraft/class_2561;
       4: astore        4
       6: aload_3
       7: ifnull        29
      10: aload         4
      12: invokeinterface #417,  1          // InterfaceMethod net/minecraft/class_2561.method_27661:()Lnet/minecraft/class_5250;
      17: aload_3
      18: aload_2
      19: invokedynamic #437,  0            // InvokeDynamic #1:apply:(Lio/github/notenoughupdates/moulconfig/common/ClickType;Ljava/lang/String;)Ljava/util/function/UnaryOperator;
      24: invokevirtual #443                // Method net/minecraft/class_5250.method_27694:(Ljava/util/function/UnaryOperator;)Lnet/minecraft/class_5250;
      27: astore        4
      29: aload_0
      30: getfield      #68                 // Field mc:Lnet/minecraft/class_310;
      33: getfield      #447                // Field net/minecraft/class_310.field_1705:Lnet/minecraft/class_329;
      36: invokevirtual #453                // Method net/minecraft/class_329.method_1743:()Lnet/minecraft/class_338;
      39: aload         4
      41: invokevirtual #459                // Method net/minecraft/class_338.method_1812:(Lnet/minecraft/class_2561;)V
      44: return

  public io.github.notenoughupdates.moulconfig.common.text.StructuredText getKeyName(int);
    Code:
       0: iload_1
       1: invokestatic  #469                // Method io/github/notenoughupdates/moulconfig/platform/ModernKeybindHelper.getKeyName:(I)Lio/github/notenoughupdates/moulconfig/common/text/StructuredText;
       4: areturn

  public io.github.notenoughupdates.moulconfig.common.text.StructuredText$Mutable createLiteral(java.lang.String);
    Code:
       0: aload_1
       1: invokestatic  #476                // InterfaceMethod net/minecraft/class_2561.method_43470:(Ljava/lang/String;)Lnet/minecraft/class_5250;
       4: invokestatic  #477                // Method wrap:(Lnet/minecraft/class_5250;)Lio/github/notenoughupdates/moulconfig/common/text/StructuredText$Mutable;
       7: areturn

  public io.github.notenoughupdates.moulconfig.common.text.StructuredText$Mutable createTranslatable(java.lang.String, io.github.notenoughupdates.moulconfig.common.text.StructuredText...);
    Code:
       0: aload_1
       1: aload_2
       2: invokestatic  #485                // InterfaceMethod java/util/stream/Stream.of:([Ljava/lang/Object;)Ljava/util/stream/Stream;
       5: invokedynamic #491,  0            // InvokeDynamic #2:apply:()Ljava/util/function/Function;
      10: invokeinterface #495,  2          // InterfaceMethod java/util/stream/Stream.map:(Ljava/util/function/Function;)Ljava/util/stream/Stream;
      15: invokeinterface #499,  1          // InterfaceMethod java/util/stream/Stream.toArray:()[Ljava/lang/Object;
      20: invokestatic  #503                // InterfaceMethod net/minecraft/class_2561.method_43469:(Ljava/lang/String;[Ljava/lang/Object;)Lnet/minecraft/class_5250;
      23: invokestatic  #477                // Method wrap:(Lnet/minecraft/class_5250;)Lio/github/notenoughupdates/moulconfig/common/text/StructuredText$Mutable;
      26: areturn

  public io.github.notenoughupdates.moulconfig.common.text.StructuredText createStructuredTextInternal(java.lang.Object);
    Code:
       0: aload_1
       1: instanceof    #413                // class net/minecraft/class_2561
       4: ifeq          17
       7: aload_1
       8: checkcast     #413                // class net/minecraft/class_2561
      11: astore_2
      12: aload_2
      13: invokestatic  #509                // Method wrap:(Lnet/minecraft/class_2561;)Lio/github/notenoughupdates/moulconfig/common/text/StructuredText;
      16: areturn
      17: aconst_null
      18: areturn

  public static net.minecraft.class_332 makeDrawContext();
    Code:
       0: invokestatic  #66                 // Method net/minecraft/class_310.method_1551:()Lnet/minecraft/class_310;
       3: astore_0
       4: new           #516                // class net/minecraft/class_332
       7: dup
       8: aload_0
       9: aload_0
      10: getfield      #520                // Field net/minecraft/class_310.field_1773:Lnet/minecraft/class_757;
      13: getfield      #526                // Field net/minecraft/class_757.field_59966:Lnet/minecraft/class_11246;
      16: aload_0
      17: getfield      #307                // Field net/minecraft/class_310.field_1729:Lnet/minecraft/class_312;
      20: aload_0
      21: invokevirtual #311                // Method net/minecraft/class_310.method_22683:()Lnet/minecraft/class_1041;
      24: invokevirtual #317                // Method net/minecraft/class_312.method_68879:(Lnet/minecraft/class_1041;)D
      27: d2i
      28: aload_0
      29: getfield      #307                // Field net/minecraft/class_310.field_1729:Lnet/minecraft/class_312;
      32: aload_0
      33: invokevirtual #311                // Method net/minecraft/class_310.method_22683:()Lnet/minecraft/class_1041;
      36: invokevirtual #320                // Method net/minecraft/class_312.method_68883:(Lnet/minecraft/class_1041;)D
      39: d2i
      40: invokespecial #529                // Method net/minecraft/class_332."<init>":(Lnet/minecraft/class_310;Lnet/minecraft/class_11246;II)V
      43: areturn

  public io.github.notenoughupdates.moulconfig.common.RenderContext provideTopLevelRenderContext();
    Code:
       0: new           #533                // class io/github/notenoughupdates/moulconfig/platform/MoulConfigRenderContext
       3: dup
       4: invokestatic  #535                // Method makeDrawContext:()Lnet/minecraft/class_332;
       7: invokespecial #538                // Method io/github/notenoughupdates/moulconfig/platform/MoulConfigRenderContext."<init>":(Lnet/minecraft/class_332;)V
      10: areturn

  public void openWrappedScreen(net.minecraft.class_437);
    Code:
       0: aload_0
       1: getfield      #68                 // Field mc:Lnet/minecraft/class_310;
       4: aload_1
       5: invokevirtual #543                // Method net/minecraft/class_310.method_1507:(Lnet/minecraft/class_437;)V
       8: return

  public void openWrappedScreen(io.github.notenoughupdates.moulconfig.gui.GuiContext);
    Code:
       0: aload_0
       1: new           #548                // class io/github/notenoughupdates/moulconfig/platform/MoulConfigScreenComponent
       4: dup
       5: invokestatic  #551                // InterfaceMethod net/minecraft/class_2561.method_43473:()Lnet/minecraft/class_5250;
       8: aload_1
       9: aconst_null
      10: invokespecial #554                // Method io/github/notenoughupdates/moulconfig/platform/MoulConfigScreenComponent."<init>":(Lnet/minecraft/class_2561;Lio/github/notenoughupdates/moulconfig/gui/GuiContext;Lnet/minecraft/class_437;)V
      13: invokevirtual #556                // Method openWrappedScreen:(Lnet/minecraft/class_437;)V
      16: return

  public void registerPlatformTypeMorphisms(io.github.notenoughupdates.moulconfig.xml.XMLUniverse);
    Code:
       0: aload_1
       1: new           #26                 // class io/github/notenoughupdates/moulconfig/platform/BoxNativeMorphisms$StructuredTextMorphism
       4: dup
       5: invokespecial #561                // Method io/github/notenoughupdates/moulconfig/platform/BoxNativeMorphisms$StructuredTextMorphism."<init>":()V
       8: invokevirtual #567                // Method io/github/notenoughupdates/moulconfig/xml/XMLUniverse.registerTypeMorphism:(Lio/github/notenoughupdates/moulconfig/xml/ParametricTypeMorphism;)V
      11: return

  public void copyToClipboard(java.lang.String);
    Code:
       0: aload_0
       1: getfield      #68                 // Field mc:Lnet/minecraft/class_310;
       4: getfield      #574                // Field net/minecraft/class_310.field_1774:Lnet/minecraft/class_309;
       7: aload_1
       8: invokevirtual #579                // Method net/minecraft/class_309.method_1455:(Ljava/lang/String;)V
      11: return

  public java.lang.String copyFromClipboard();
    Code:
       0: aload_0
       1: getfield      #68                 // Field mc:Lnet/minecraft/class_310;
       4: getfield      #574                // Field net/minecraft/class_310.field_1774:Lnet/minecraft/class_309;
       7: invokevirtual #584                // Method net/minecraft/class_309.method_1460:()Ljava/lang/String;
      10: areturn

  private static net.minecraft.class_2583 lambda$sendClickableChatMessage$0(io.github.notenoughupdates.moulconfig.common.ClickType, java.lang.String, net.minecraft.class_2583);
    Code:
       0: aload_2
       1: getstatic     #588                // Field io/github/notenoughupdates/moulconfig/platform/MoulConfigPlatform$3.$SwitchMap$io$github$notenoughupdates$moulconfig$common$ClickType:[I
       4: aload_0
       5: invokevirtual #593                // Method io/github/notenoughupdates/moulconfig/common/ClickType.ordinal:()I
       8: iaload
       9: lookupswitch  { // 2
                     1: 46
                     2: 60
               default: 36
          }
      36: new           #597                // class java/lang/MatchException
      39: dup
      40: aconst_null
      41: aconst_null
      42: invokespecial #600                // Method java/lang/MatchException."<init>":(Ljava/lang/String;Ljava/lang/Throwable;)V
      45: athrow
      46: new           #31                 // class net/minecraft/class_2558$class_10608
      49: dup
      50: aload_1
      51: invokestatic  #606                // Method java/net/URI.create:(Ljava/lang/String;)Ljava/net/URI;
      54: invokespecial #609                // Method net/minecraft/class_2558$class_10608."<init>":(Ljava/net/URI;)V
      57: goto          68
      60: new           #36                 // class net/minecraft/class_2558$class_10609
      63: dup
      64: aload_1
      65: invokespecial #611                // Method net/minecraft/class_2558$class_10609."<init>":(Ljava/lang/String;)V
      68: invokevirtual #615                // Method net/minecraft/class_2583.method_10958:(Lnet/minecraft/class_2558;)Lnet/minecraft/class_2583;
      71: areturn

  static {};
    Code:
       0: ldc           #2                  // class io/github/notenoughupdates/moulconfig/platform/MoulConfigPlatform
       2: invokevirtual #623                // Method java/lang/Class.desiredAssertionStatus:()Z
       5: ifne          12
       8: iconst_1
       9: goto          13
      12: iconst_0
      13: putstatic     #222                // Field $assertionsDisabled:Z
      16: ldc           #2                  // class io/github/notenoughupdates/moulconfig/platform/MoulConfigPlatform
      18: invokestatic  #628                // Method org/slf4j/LoggerFactory.getLogger:(Ljava/lang/Class;)Lorg/slf4j/Logger;
      21: putstatic     #630                // Field log:Lorg/slf4j/Logger;
      24: return
}
