Compiled from "ClickLogic.java"
public class me.bombo.bomboaddons.ClickLogic {
  private static java.util.List<me.bombo.bomboaddons.ClickLogic$ClickTarget> targets;

  private static boolean debugMode;

  private static final com.google.gson.Gson GSON;

  private static final java.io.File CONFIG_FILE;

  private static final java.util.Map<java.lang.String, java.lang.Integer> KEY_MAP;

  public me.bombo.bomboaddons.ClickLogic();
    Code:
       0: aload_0
       1: invokespecial #51                 // Method java/lang/Object."<init>":()V
       4: return

  public static void setTarget(java.lang.String, java.lang.String, java.lang.String, java.lang.String, boolean);
    Code:
       0: getstatic     #62                 // Field KEY_MAP:Ljava/util/Map;
       3: aload_2
       4: invokevirtual #68                 // Method java/lang/String.toLowerCase:()Ljava/lang/String;
       7: iconst_m1
       8: invokestatic  #74                 // Method java/lang/Integer.valueOf:(I)Ljava/lang/Integer;
      11: invokeinterface #78,  3           // InterfaceMethod java/util/Map.getOrDefault:(Ljava/lang/Object;Ljava/lang/Object;)Ljava/lang/Object;
      16: checkcast     #70                 // class java/lang/Integer
      19: invokevirtual #82                 // Method java/lang/Integer.intValue:()I
      22: istore        5
      24: getstatic     #84                 // Field targets:Ljava/util/List;
      27: new           #7                  // class me/bombo/bomboaddons/ClickLogic$ClickTarget
      30: dup
      31: aload_0
      32: aload_1
      33: aload_2
      34: iload         5
      36: aload_3
      37: iload         4
      39: invokespecial #87                 // Method me/bombo/bomboaddons/ClickLogic$ClickTarget."<init>":(Ljava/lang/String;Ljava/lang/String;Ljava/lang/String;ILjava/lang/String;Z)V
      42: invokeinterface #93,  2           // InterfaceMethod java/util/List.add:(Ljava/lang/Object;)Z
      47: pop
      48: invokestatic  #96                 // Method saveTargets:()V
      51: return

  public static java.util.List<me.bombo.bomboaddons.ClickLogic$ClickTarget> getTargets();
    Code:
       0: getstatic     #84                 // Field targets:Ljava/util/List;
       3: areturn

  public static void removeTarget(int);
    Code:
       0: iload_0
       1: iflt          29
       4: iload_0
       5: getstatic     #84                 // Field targets:Ljava/util/List;
       8: invokeinterface #108,  1          // InterfaceMethod java/util/List.size:()I
      13: if_icmpge     29
      16: getstatic     #84                 // Field targets:Ljava/util/List;
      19: iload_0
      20: invokeinterface #112,  2          // InterfaceMethod java/util/List.remove:(I)Ljava/lang/Object;
      25: pop
      26: invokestatic  #96                 // Method saveTargets:()V
      29: return

  public static void removeTargetById(java.lang.String);
    Code:
       0: aload_0
       1: invokestatic  #123                // Method java/util/UUID.fromString:(Ljava/lang/String;)Ljava/util/UUID;
       4: astore_1
       5: getstatic     #84                 // Field targets:Ljava/util/List;
       8: aload_1
       9: invokedynamic #142,  0            // InvokeDynamic #0:test:(Ljava/util/UUID;)Ljava/util/function/Predicate;
      14: invokeinterface #146,  2          // InterfaceMethod java/util/List.removeIf:(Ljava/util/function/Predicate;)Z
      19: pop
      20: invokestatic  #96                 // Method saveTargets:()V
      23: goto          27
      26: astore_1
      27: return
    Exception table:
       from    to  target type
           0    23    26   Class java/lang/IllegalArgumentException

  public static java.io.File getConfigFile();
    Code:
       0: getstatic     #152                // Field CONFIG_FILE:Ljava/io/File;
       3: areturn

  public static void toggleDebug();
    Code:
       0: getstatic     #155                // Field debugMode:Z
       3: ifne          10
       6: iconst_1
       7: goto          11
      10: iconst_0
      11: putstatic     #155                // Field debugMode:Z
      14: return

  public static boolean isDebugMode();
    Code:
       0: getstatic     #155                // Field debugMode:Z
       3: ireturn

  public static void onKeyPressed(int);
    Code:
       0: invokestatic  #163                // Method me/bombo/bomboaddons/BomboConfig.get:()Lme/bombo/bomboaddons/BomboConfig$Settings;
       3: getfield      #166                // Field me/bombo/bomboaddons/BomboConfig$Settings.chestClicker:Z
       6: ifne          10
       9: return
      10: invokestatic  #172                // Method net/minecraft/class_310.method_1551:()Lnet/minecraft/class_310;
      13: astore_1
      14: aload_1
      15: getfield      #176                // Field net/minecraft/class_310.field_1755:Lnet/minecraft/class_437;
      18: astore_3
      19: aload_3
      20: instanceof    #178                // class net/minecraft/class_465
      23: ifeq          244
      26: aload_3
      27: checkcast     #178                // class net/minecraft/class_465
      30: astore_2
      31: aload_2
      32: invokevirtual #182                // Method net/minecraft/class_465.method_25440:()Lnet/minecraft/class_2561;
      35: invokeinterface #187,  1          // InterfaceMethod net/minecraft/class_2561.getString:()Ljava/lang/String;
      40: invokevirtual #68                 // Method java/lang/String.toLowerCase:()Ljava/lang/String;
      43: astore_3
      44: getstatic     #155                // Field debugMode:Z
      47: ifeq          72
      50: aload_1
      51: getfield      #191                // Field net/minecraft/class_310.field_1724:Lnet/minecraft/class_746;
      54: iload_0
      55: iload_0
      56: invokestatic  #195                // Method getKeyName:(I)Ljava/lang/String;
      59: aload_3
      60: invokedynamic #207,  0            // InvokeDynamic #1:makeConcatWithConstants:(ILjava/lang/String;Ljava/lang/String;)Ljava/lang/String;
      65: invokestatic  #211                // InterfaceMethod net/minecraft/class_2561.method_43470:(Ljava/lang/String;)Lnet/minecraft/class_5250;
      68: iconst_0
      69: invokevirtual #217                // Method net/minecraft/class_746.method_7353:(Lnet/minecraft/class_2561;Z)V
      72: getstatic     #84                 // Field targets:Ljava/util/List;
      75: invokeinterface #221,  1          // InterfaceMethod java/util/List.iterator:()Ljava/util/Iterator;
      80: astore        4
      82: aload         4
      84: invokeinterface #226,  1          // InterfaceMethod java/util/Iterator.hasNext:()Z
      89: ifeq          241
      92: aload         4
      94: invokeinterface #230,  1          // InterfaceMethod java/util/Iterator.next:()Ljava/lang/Object;
      99: checkcast     #7                  // class me/bombo/bomboaddons/ClickLogic$ClickTarget
     102: astore        5
     104: aload         5
     106: getfield      #232                // Field me/bombo/bomboaddons/ClickLogic$ClickTarget.auto:Z
     109: ifeq          115
     112: goto          82
     115: getstatic     #155                // Field debugMode:Z
     118: ifeq          157
     121: aload_1
     122: getfield      #191                // Field net/minecraft/class_310.field_1724:Lnet/minecraft/class_746;
     125: aload         5
     127: getfield      #234                // Field me/bombo/bomboaddons/ClickLogic$ClickTarget.item:Ljava/lang/String;
     130: aload         5
     132: getfield      #236                // Field me/bombo/bomboaddons/ClickLogic$ClickTarget.keyCode:I
     135: aload         5
     137: getfield      #238                // Field me/bombo/bomboaddons/ClickLogic$ClickTarget.keyName:Ljava/lang/String;
     140: aload         5
     142: getfield      #240                // Field me/bombo/bomboaddons/ClickLogic$ClickTarget.gui:Ljava/lang/String;
     145: invokedynamic #245,  0            // InvokeDynamic #2:makeConcatWithConstants:(Ljava/lang/String;ILjava/lang/String;Ljava/lang/String;)Ljava/lang/String;
     150: invokestatic  #211                // InterfaceMethod net/minecraft/class_2561.method_43470:(Ljava/lang/String;)Lnet/minecraft/class_5250;
     153: iconst_0
     154: invokevirtual #217                // Method net/minecraft/class_746.method_7353:(Lnet/minecraft/class_2561;Z)V
     157: aload         5
     159: getfield      #236                // Field me/bombo/bomboaddons/ClickLogic$ClickTarget.keyCode:I
     162: iconst_m1
     163: if_icmpeq     238
     166: iload_0
     167: aload         5
     169: getfield      #236                // Field me/bombo/bomboaddons/ClickLogic$ClickTarget.keyCode:I
     172: if_icmpne     238
     175: aload         5
     177: getfield      #240                // Field me/bombo/bomboaddons/ClickLogic$ClickTarget.gui:Ljava/lang/String;
     180: ldc           #247                // String all
     182: invokevirtual #250                // Method java/lang/String.equals:(Ljava/lang/Object;)Z
     185: ifne          200
     188: aload_3
     189: aload         5
     191: getfield      #240                // Field me/bombo/bomboaddons/ClickLogic$ClickTarget.gui:Ljava/lang/String;
     194: invokevirtual #254                // Method java/lang/String.contains:(Ljava/lang/CharSequence;)Z
     197: ifeq          210
     200: aload         5
     202: aload_1
     203: aload_2
     204: invokestatic  #258                // Method executeClick:(Lme/bombo/bomboaddons/ClickLogic$ClickTarget;Lnet/minecraft/class_310;Lnet/minecraft/class_465;)V
     207: goto          238
     210: getstatic     #155                // Field debugMode:Z
     213: ifeq          238
     216: aload_1
     217: getfield      #191                // Field net/minecraft/class_310.field_1724:Lnet/minecraft/class_746;
     220: aload_3
     221: aload         5
     223: getfield      #240                // Field me/bombo/bomboaddons/ClickLogic$ClickTarget.gui:Ljava/lang/String;
     226: invokedynamic #263,  0            // InvokeDynamic #3:makeConcatWithConstants:(Ljava/lang/String;Ljava/lang/String;)Ljava/lang/String;
     231: invokestatic  #211                // InterfaceMethod net/minecraft/class_2561.method_43470:(Ljava/lang/String;)Lnet/minecraft/class_5250;
     234: iconst_0
     235: invokevirtual #217                // Method net/minecraft/class_746.method_7353:(Lnet/minecraft/class_2561;Z)V
     238: goto          82
     241: goto          278
     244: getstatic     #155                // Field debugMode:Z
     247: ifeq          278
     250: aload_1
     251: getfield      #191                // Field net/minecraft/class_310.field_1724:Lnet/minecraft/class_746;
     254: ifnull        278
     257: aload_1
     258: getfield      #191                // Field net/minecraft/class_310.field_1724:Lnet/minecraft/class_746;
     261: iload_0
     262: iload_0
     263: invokestatic  #195                // Method getKeyName:(I)Ljava/lang/String;
     266: invokedynamic #268,  0            // InvokeDynamic #4:makeConcatWithConstants:(ILjava/lang/String;)Ljava/lang/String;
     271: invokestatic  #211                // InterfaceMethod net/minecraft/class_2561.method_43470:(Ljava/lang/String;)Lnet/minecraft/class_5250;
     274: iconst_0
     275: invokevirtual #217                // Method net/minecraft/class_746.method_7353:(Lnet/minecraft/class_2561;Z)V
     278: return

  public static void onGuiOpen(net.minecraft.class_465);
    Code:
       0: invokestatic  #163                // Method me/bombo/bomboaddons/BomboConfig.get:()Lme/bombo/bomboaddons/BomboConfig$Settings;
       3: getfield      #280                // Field me/bombo/bomboaddons/BomboConfig$Settings.autoClicker:Z
       6: ifne          10
       9: return
      10: invokestatic  #172                // Method net/minecraft/class_310.method_1551:()Lnet/minecraft/class_310;
      13: astore_1
      14: aload_0
      15: invokevirtual #182                // Method net/minecraft/class_465.method_25440:()Lnet/minecraft/class_2561;
      18: invokeinterface #187,  1          // InterfaceMethod net/minecraft/class_2561.getString:()Ljava/lang/String;
      23: invokevirtual #68                 // Method java/lang/String.toLowerCase:()Ljava/lang/String;
      26: astore_2
      27: getstatic     #155                // Field debugMode:Z
      30: ifeq          57
      33: aload_1
      34: getfield      #191                // Field net/minecraft/class_310.field_1724:Lnet/minecraft/class_746;
      37: ifnull        57
      40: aload_1
      41: getfield      #191                // Field net/minecraft/class_310.field_1724:Lnet/minecraft/class_746;
      44: aload_2
      45: invokedynamic #285,  0            // InvokeDynamic #5:makeConcatWithConstants:(Ljava/lang/String;)Ljava/lang/String;
      50: invokestatic  #211                // InterfaceMethod net/minecraft/class_2561.method_43470:(Ljava/lang/String;)Lnet/minecraft/class_5250;
      53: iconst_0
      54: invokevirtual #217                // Method net/minecraft/class_746.method_7353:(Lnet/minecraft/class_2561;Z)V
      57: new           #287                // class java/lang/Thread
      60: dup
      61: aload_1
      62: aload_0
      63: aload_2
      64: invokedynamic #297,  0            // InvokeDynamic #6:run:(Lnet/minecraft/class_310;Lnet/minecraft/class_465;Ljava/lang/String;)Ljava/lang/Runnable;
      69: invokespecial #300                // Method java/lang/Thread."<init>":(Ljava/lang/Runnable;)V
      72: invokevirtual #303                // Method java/lang/Thread.start:()V
      75: return

  private static java.lang.String getKeyName(int);
    Code:
       0: getstatic     #62                 // Field KEY_MAP:Ljava/util/Map;
       3: invokeinterface #307,  1          // InterfaceMethod java/util/Map.entrySet:()Ljava/util/Set;
       8: invokeinterface #310,  1          // InterfaceMethod java/util/Set.iterator:()Ljava/util/Iterator;
      13: astore_1
      14: aload_1
      15: invokeinterface #226,  1          // InterfaceMethod java/util/Iterator.hasNext:()Z
      20: ifeq          62
      23: aload_1
      24: invokeinterface #230,  1          // InterfaceMethod java/util/Iterator.next:()Ljava/lang/Object;
      29: checkcast     #17                 // class java/util/Map$Entry
      32: astore_2
      33: aload_2
      34: invokeinterface #313,  1          // InterfaceMethod java/util/Map$Entry.getValue:()Ljava/lang/Object;
      39: checkcast     #70                 // class java/lang/Integer
      42: invokevirtual #82                 // Method java/lang/Integer.intValue:()I
      45: iload_0
      46: if_icmpne     59
      49: aload_2
      50: invokeinterface #316,  1          // InterfaceMethod java/util/Map$Entry.getKey:()Ljava/lang/Object;
      55: checkcast     #64                 // class java/lang/String
      58: areturn
      59: goto          14
      62: ldc_w         #318                // String unknown
      65: areturn

  private static void executeClick(me.bombo.bomboaddons.ClickLogic$ClickTarget, net.minecraft.class_310, net.minecraft.class_465);
    Code:
       0: aload_0
       1: getfield      #234                // Field me/bombo/bomboaddons/ClickLogic$ClickTarget.item:Ljava/lang/String;
       4: ldc_w         #325                // String /
       7: invokevirtual #329                // Method java/lang/String.startsWith:(Ljava/lang/String;)Z
      10: ifeq          52
      13: aload_1
      14: getfield      #191                // Field net/minecraft/class_310.field_1724:Lnet/minecraft/class_746;
      17: getfield      #333                // Field net/minecraft/class_746.field_3944:Lnet/minecraft/class_634;
      20: aload_0
      21: getfield      #234                // Field me/bombo/bomboaddons/ClickLogic$ClickTarget.item:Ljava/lang/String;
      24: iconst_1
      25: invokevirtual #336                // Method java/lang/String.substring:(I)Ljava/lang/String;
      28: invokevirtual #341                // Method net/minecraft/class_634.method_45730:(Ljava/lang/String;)V
      31: aload_1
      32: getfield      #191                // Field net/minecraft/class_310.field_1724:Lnet/minecraft/class_746;
      35: aload_0
      36: getfield      #234                // Field me/bombo/bomboaddons/ClickLogic$ClickTarget.item:Ljava/lang/String;
      39: invokedynamic #344,  0            // InvokeDynamic #7:makeConcatWithConstants:(Ljava/lang/String;)Ljava/lang/String;
      44: invokestatic  #211                // InterfaceMethod net/minecraft/class_2561.method_43470:(Ljava/lang/String;)Lnet/minecraft/class_5250;
      47: iconst_1
      48: invokevirtual #217                // Method net/minecraft/class_746.method_7353:(Lnet/minecraft/class_2561;Z)V
      51: return
      52: aload_2
      53: invokevirtual #348                // Method net/minecraft/class_465.method_17577:()Lnet/minecraft/class_1703;
      56: getfield      #354                // Field net/minecraft/class_1703.field_7761:Lnet/minecraft/class_2371;
      59: astore_3
      60: aload_3
      61: invokeinterface #108,  1          // InterfaceMethod java/util/List.size:()I
      66: istore        4
      68: iconst_0
      69: istore        5
      71: iload         5
      73: iload         4
      75: if_icmpge     462
      78: aload_3
      79: iload         5
      81: invokeinterface #356,  2          // InterfaceMethod java/util/List.get:(I)Ljava/lang/Object;
      86: checkcast     #358                // class net/minecraft/class_1735
      89: astore        6
      91: aload         6
      93: invokevirtual #362                // Method net/minecraft/class_1735.method_7677:()Lnet/minecraft/class_1799;
      96: astore        7
      98: aload         7
     100: invokevirtual #367                // Method net/minecraft/class_1799.method_7960:()Z
     103: ifeq          109
     106: goto          456
     109: aload         7
     111: invokevirtual #370                // Method net/minecraft/class_1799.method_7964:()Lnet/minecraft/class_2561;
     114: invokeinterface #187,  1          // InterfaceMethod net/minecraft/class_2561.getString:()Ljava/lang/String;
     119: invokevirtual #68                 // Method java/lang/String.toLowerCase:()Ljava/lang/String;
     122: astore        8
     124: iconst_0
     125: istore        9
     127: aload_0
     128: getfield      #234                // Field me/bombo/bomboaddons/ClickLogic$ClickTarget.item:Ljava/lang/String;
     131: ldc_w         #372                // String l:
     134: invokevirtual #329                // Method java/lang/String.startsWith:(Ljava/lang/String;)Z
     137: ifeq          235
     140: aload_0
     141: getfield      #234                // Field me/bombo/bomboaddons/ClickLogic$ClickTarget.item:Ljava/lang/String;
     144: iconst_2
     145: invokevirtual #336                // Method java/lang/String.substring:(I)Ljava/lang/String;
     148: invokevirtual #68                 // Method java/lang/String.toLowerCase:()Ljava/lang/String;
     151: astore        10
     153: aload         7
     155: aload_1
     156: getfield      #376                // Field net/minecraft/class_310.field_1687:Lnet/minecraft/class_638;
     159: invokestatic  #380                // InterfaceMethod net/minecraft/class_1792$class_9635.method_59528:(Lnet/minecraft/class_1937;)Lnet/minecraft/class_1792$class_9635;
     162: aload_1
     163: getfield      #191                // Field net/minecraft/class_310.field_1724:Lnet/minecraft/class_746;
     166: getstatic     #384                // Field net/minecraft/class_1836$class_1837.field_41070:Lnet/minecraft/class_1836$class_1837;
     169: invokevirtual #388                // Method net/minecraft/class_1799.method_7950:(Lnet/minecraft/class_1792$class_9635;Lnet/minecraft/class_1657;Lnet/minecraft/class_1836;)Ljava/util/List;
     172: astore        11
     174: aload         11
     176: invokeinterface #221,  1          // InterfaceMethod java/util/List.iterator:()Ljava/util/Iterator;
     181: astore        12
     183: aload         12
     185: invokeinterface #226,  1          // InterfaceMethod java/util/Iterator.hasNext:()Z
     190: ifeq          232
     193: aload         12
     195: invokeinterface #230,  1          // InterfaceMethod java/util/Iterator.next:()Ljava/lang/Object;
     200: checkcast     #184                // class net/minecraft/class_2561
     203: astore        13
     205: aload         13
     207: invokeinterface #187,  1          // InterfaceMethod net/minecraft/class_2561.getString:()Ljava/lang/String;
     212: invokevirtual #68                 // Method java/lang/String.toLowerCase:()Ljava/lang/String;
     215: aload         10
     217: invokevirtual #254                // Method java/lang/String.contains:(Ljava/lang/CharSequence;)Z
     220: ifeq          229
     223: iconst_1
     224: istore        9
     226: goto          232
     229: goto          183
     232: goto          330
     235: aload_0
     236: getfield      #234                // Field me/bombo/bomboaddons/ClickLogic$ClickTarget.item:Ljava/lang/String;
     239: ldc_w         #325                // String /
     242: invokevirtual #329                // Method java/lang/String.startsWith:(Ljava/lang/String;)Z
     245: ifeq          297
     248: aload_0
     249: getfield      #234                // Field me/bombo/bomboaddons/ClickLogic$ClickTarget.item:Ljava/lang/String;
     252: ldc_w         #325                // String /
     255: invokevirtual #391                // Method java/lang/String.endsWith:(Ljava/lang/String;)Z
     258: ifeq          297
     261: aload_0
     262: getfield      #234                // Field me/bombo/bomboaddons/ClickLogic$ClickTarget.item:Ljava/lang/String;
     265: iconst_1
     266: aload_0
     267: getfield      #234                // Field me/bombo/bomboaddons/ClickLogic$ClickTarget.item:Ljava/lang/String;
     270: invokevirtual #394                // Method java/lang/String.length:()I
     273: iconst_1
     274: isub
     275: invokevirtual #397                // Method java/lang/String.substring:(II)Ljava/lang/String;
     278: astore        10
     280: aload         8
     282: aload         10
     284: invokedynamic #400,  0            // InvokeDynamic #8:makeConcatWithConstants:(Ljava/lang/String;)Ljava/lang/String;
     289: invokevirtual #403                // Method java/lang/String.matches:(Ljava/lang/String;)Z
     292: istore        9
     294: goto          311
     297: aload         8
     299: aload_0
     300: getfield      #234                // Field me/bombo/bomboaddons/ClickLogic$ClickTarget.item:Ljava/lang/String;
     303: invokevirtual #68                 // Method java/lang/String.toLowerCase:()Ljava/lang/String;
     306: invokevirtual #254                // Method java/lang/String.contains:(Ljava/lang/CharSequence;)Z
     309: istore        9
     311: goto          330
     314: astore        10
     316: aload         8
     318: aload_0
     319: getfield      #234                // Field me/bombo/bomboaddons/ClickLogic$ClickTarget.item:Ljava/lang/String;
     322: invokevirtual #68                 // Method java/lang/String.toLowerCase:()Ljava/lang/String;
     325: invokevirtual #254                // Method java/lang/String.contains:(Ljava/lang/CharSequence;)Z
     328: istore        9
     330: iload         9
     332: ifeq          456
     335: aload_1
     336: getfield      #407                // Field net/minecraft/class_310.field_1761:Lnet/minecraft/class_636;
     339: ifnull        455
     342: aload_1
     343: getfield      #191                // Field net/minecraft/class_310.field_1724:Lnet/minecraft/class_746;
     346: ifnull        455
     349: iconst_0
     350: istore        10
     352: aload_0
     353: getfield      #409                // Field me/bombo/bomboaddons/ClickLogic$ClickTarget.type:Ljava/lang/String;
     356: ldc_w         #411                // String right
     359: invokevirtual #414                // Method java/lang/String.equalsIgnoreCase:(Ljava/lang/String;)Z
     362: ifeq          371
     365: iconst_1
     366: istore        10
     368: goto          387
     371: aload_0
     372: getfield      #409                // Field me/bombo/bomboaddons/ClickLogic$ClickTarget.type:Ljava/lang/String;
     375: ldc_w         #416                // String middle
     378: invokevirtual #414                // Method java/lang/String.equalsIgnoreCase:(Ljava/lang/String;)Z
     381: ifeq          387
     384: iconst_2
     385: istore        10
     387: aload_1
     388: getfield      #407                // Field net/minecraft/class_310.field_1761:Lnet/minecraft/class_636;
     391: aload_2
     392: invokevirtual #348                // Method net/minecraft/class_465.method_17577:()Lnet/minecraft/class_1703;
     395: getfield      #419                // Field net/minecraft/class_1703.field_7763:I
     398: aload         6
     400: getfield      #422                // Field net/minecraft/class_1735.field_7874:I
     403: iload         10
     405: getstatic     #428                // Field net/minecraft/class_1713.field_7790:Lnet/minecraft/class_1713;
     408: aload_1
     409: getfield      #191                // Field net/minecraft/class_310.field_1724:Lnet/minecraft/class_746;
     412: invokevirtual #434                // Method net/minecraft/class_636.method_2906:(IIILnet/minecraft/class_1713;Lnet/minecraft/class_1657;)V
     415: aload_1
     416: getfield      #191                // Field net/minecraft/class_310.field_1724:Lnet/minecraft/class_746;
     419: aload         7
     421: invokevirtual #370                // Method net/minecraft/class_1799.method_7964:()Lnet/minecraft/class_2561;
     424: invokeinterface #187,  1          // InterfaceMethod net/minecraft/class_2561.getString:()Ljava/lang/String;
     429: aload         6
     431: getfield      #422                // Field net/minecraft/class_1735.field_7874:I
     434: aload_2
     435: invokevirtual #182                // Method net/minecraft/class_465.method_25440:()Lnet/minecraft/class_2561;
     438: invokeinterface #187,  1          // InterfaceMethod net/minecraft/class_2561.getString:()Ljava/lang/String;
     443: invokedynamic #439,  0            // InvokeDynamic #9:makeConcatWithConstants:(Ljava/lang/String;ILjava/lang/String;)Ljava/lang/String;
     448: invokestatic  #211                // InterfaceMethod net/minecraft/class_2561.method_43470:(Ljava/lang/String;)Lnet/minecraft/class_5250;
     451: iconst_1
     452: invokevirtual #217                // Method net/minecraft/class_746.method_7353:(Lnet/minecraft/class_2561;Z)V
     455: return
     456: iinc          5, 1
     459: goto          71
     462: getstatic     #155                // Field debugMode:Z
     465: ifeq          495
     468: aload_1
     469: getfield      #191                // Field net/minecraft/class_310.field_1724:Lnet/minecraft/class_746;
     472: ifnull        495
     475: aload_1
     476: getfield      #191                // Field net/minecraft/class_310.field_1724:Lnet/minecraft/class_746;
     479: aload_0
     480: getfield      #234                // Field me/bombo/bomboaddons/ClickLogic$ClickTarget.item:Ljava/lang/String;
     483: invokedynamic #442,  0            // InvokeDynamic #10:makeConcatWithConstants:(Ljava/lang/String;)Ljava/lang/String;
     488: invokestatic  #211                // InterfaceMethod net/minecraft/class_2561.method_43470:(Ljava/lang/String;)Lnet/minecraft/class_5250;
     491: iconst_0
     492: invokevirtual #217                // Method net/minecraft/class_746.method_7353:(Lnet/minecraft/class_2561;Z)V
     495: return
    Exception table:
       from    to  target type
         235   311   314   Class java/lang/Exception

  private static void saveTargets();
    Code:
       0: new           #467                // class java/io/FileWriter
       3: dup
       4: getstatic     #152                // Field CONFIG_FILE:Ljava/io/File;
       7: invokespecial #470                // Method java/io/FileWriter."<init>":(Ljava/io/File;)V
      10: astore_0
      11: getstatic     #472                // Field GSON:Lcom/google/gson/Gson;
      14: getstatic     #84                 // Field targets:Ljava/util/List;
      17: aload_0
      18: invokevirtual #478                // Method com/google/gson/Gson.toJson:(Ljava/lang/Object;Ljava/lang/Appendable;)V
      21: aload_0
      22: invokevirtual #481                // Method java/io/FileWriter.close:()V
      25: goto          44
      28: astore_1
      29: aload_0
      30: invokevirtual #481                // Method java/io/FileWriter.close:()V
      33: goto          42
      36: astore_2
      37: aload_1
      38: aload_2
      39: invokevirtual #485                // Method java/lang/Throwable.addSuppressed:(Ljava/lang/Throwable;)V
      42: aload_1
      43: athrow
      44: goto          52
      47: astore_0
      48: aload_0
      49: invokevirtual #488                // Method java/io/IOException.printStackTrace:()V
      52: return
    Exception table:
       from    to  target type
          11    21    28   Class java/lang/Throwable
          29    33    36   Class java/lang/Throwable
           0    44    47   Class java/io/IOException

  private static void loadTargets();
    Code:
       0: getstatic     #152                // Field CONFIG_FILE:Ljava/io/File;
       3: invokevirtual #497                // Method java/io/File.exists:()Z
       6: ifne          10
       9: return
      10: new           #499                // class java/io/FileReader
      13: dup
      14: getstatic     #152                // Field CONFIG_FILE:Ljava/io/File;
      17: invokespecial #500                // Method java/io/FileReader."<init>":(Ljava/io/File;)V
      20: astore_0
      21: new           #9                  // class me/bombo/bomboaddons/ClickLogic$1
      24: dup
      25: invokespecial #501                // Method me/bombo/bomboaddons/ClickLogic$1."<init>":()V
      28: invokevirtual #505                // Method me/bombo/bomboaddons/ClickLogic$1.getType:()Ljava/lang/reflect/Type;
      31: astore_1
      32: getstatic     #472                // Field GSON:Lcom/google/gson/Gson;
      35: aload_0
      36: aload_1
      37: invokevirtual #509                // Method com/google/gson/Gson.fromJson:(Ljava/io/Reader;Ljava/lang/reflect/Type;)Ljava/lang/Object;
      40: checkcast     #89                 // class java/util/List
      43: astore_2
      44: aload_2
      45: ifnull        98
      48: aload_2
      49: invokeinterface #221,  1          // InterfaceMethod java/util/List.iterator:()Ljava/util/Iterator;
      54: astore_3
      55: aload_3
      56: invokeinterface #226,  1          // InterfaceMethod java/util/Iterator.hasNext:()Z
      61: ifeq          94
      64: aload_3
      65: invokeinterface #230,  1          // InterfaceMethod java/util/Iterator.next:()Ljava/lang/Object;
      70: checkcast     #7                  // class me/bombo/bomboaddons/ClickLogic$ClickTarget
      73: astore        4
      75: aload         4
      77: getfield      #513                // Field me/bombo/bomboaddons/ClickLogic$ClickTarget.id:Ljava/util/UUID;
      80: ifnonnull     91
      83: aload         4
      85: invokestatic  #517                // Method java/util/UUID.randomUUID:()Ljava/util/UUID;
      88: putfield      #513                // Field me/bombo/bomboaddons/ClickLogic$ClickTarget.id:Ljava/util/UUID;
      91: goto          55
      94: aload_2
      95: putstatic     #84                 // Field targets:Ljava/util/List;
      98: aload_0
      99: invokevirtual #518                // Method java/io/FileReader.close:()V
     102: goto          121
     105: astore_1
     106: aload_0
     107: invokevirtual #518                // Method java/io/FileReader.close:()V
     110: goto          119
     113: astore_2
     114: aload_1
     115: aload_2
     116: invokevirtual #485                // Method java/lang/Throwable.addSuppressed:(Ljava/lang/Throwable;)V
     119: aload_1
     120: athrow
     121: goto          129
     124: astore_0
     125: aload_0
     126: invokevirtual #488                // Method java/io/IOException.printStackTrace:()V
     129: return
    Exception table:
       from    to  target type
          21    98   105   Class java/lang/Throwable
         106   110   113   Class java/lang/Throwable
          10   121   124   Class java/io/IOException

  private static void lambda$onGuiOpen$2(net.minecraft.class_310, net.minecraft.class_465, java.lang.String);
    Code:
       0: ldc2_w        #526                // long 100l
       3: invokestatic  #531                // Method java/lang/Thread.sleep:(J)V
       6: goto          14
       9: astore_3
      10: aload_3
      11: invokevirtual #532                // Method java/lang/InterruptedException.printStackTrace:()V
      14: aload_0
      15: aload_0
      16: aload_1
      17: aload_2
      18: invokedynamic #537,  0            // InvokeDynamic #11:run:(Lnet/minecraft/class_310;Lnet/minecraft/class_465;Ljava/lang/String;)Ljava/lang/Runnable;
      23: invokevirtual #540                // Method net/minecraft/class_310.execute:(Ljava/lang/Runnable;)V
      26: return
    Exception table:
       from    to  target type
           0     6     9   Class java/lang/InterruptedException

  private static void lambda$onGuiOpen$1(net.minecraft.class_310, net.minecraft.class_465, java.lang.String);
    Code:
       0: aload_0
       1: getfield      #176                // Field net/minecraft/class_310.field_1755:Lnet/minecraft/class_437;
       4: aload_1
       5: if_acmpeq     9
       8: return
       9: getstatic     #84                 // Field targets:Ljava/util/List;
      12: invokeinterface #221,  1          // InterfaceMethod java/util/List.iterator:()Ljava/util/Iterator;
      17: astore_3
      18: aload_3
      19: invokeinterface #226,  1          // InterfaceMethod java/util/Iterator.hasNext:()Z
      24: ifeq          118
      27: aload_3
      28: invokeinterface #230,  1          // InterfaceMethod java/util/Iterator.next:()Ljava/lang/Object;
      33: checkcast     #7                  // class me/bombo/bomboaddons/ClickLogic$ClickTarget
      36: astore        4
      38: aload         4
      40: getfield      #232                // Field me/bombo/bomboaddons/ClickLogic$ClickTarget.auto:Z
      43: ifne          49
      46: goto          18
      49: aload         4
      51: getfield      #240                // Field me/bombo/bomboaddons/ClickLogic$ClickTarget.gui:Ljava/lang/String;
      54: ldc           #247                // String all
      56: invokevirtual #250                // Method java/lang/String.equals:(Ljava/lang/Object;)Z
      59: ifne          74
      62: aload_2
      63: aload         4
      65: getfield      #240                // Field me/bombo/bomboaddons/ClickLogic$ClickTarget.gui:Ljava/lang/String;
      68: invokevirtual #254                // Method java/lang/String.contains:(Ljava/lang/CharSequence;)Z
      71: ifeq          115
      74: getstatic     #155                // Field debugMode:Z
      77: ifeq          108
      80: aload_0
      81: getfield      #191                // Field net/minecraft/class_310.field_1724:Lnet/minecraft/class_746;
      84: ifnull        108
      87: aload_0
      88: getfield      #191                // Field net/minecraft/class_310.field_1724:Lnet/minecraft/class_746;
      91: aload         4
      93: getfield      #234                // Field me/bombo/bomboaddons/ClickLogic$ClickTarget.item:Ljava/lang/String;
      96: invokedynamic #544,  0            // InvokeDynamic #12:makeConcatWithConstants:(Ljava/lang/String;)Ljava/lang/String;
     101: invokestatic  #211                // InterfaceMethod net/minecraft/class_2561.method_43470:(Ljava/lang/String;)Lnet/minecraft/class_5250;
     104: iconst_0
     105: invokevirtual #217                // Method net/minecraft/class_746.method_7353:(Lnet/minecraft/class_2561;Z)V
     108: aload         4
     110: aload_0
     111: aload_1
     112: invokestatic  #258                // Method executeClick:(Lme/bombo/bomboaddons/ClickLogic$ClickTarget;Lnet/minecraft/class_310;Lnet/minecraft/class_465;)V
     115: goto          18
     118: return

  private static boolean lambda$removeTargetById$0(java.util.UUID, me.bombo.bomboaddons.ClickLogic$ClickTarget);
    Code:
       0: aload_1
       1: getfield      #513                // Field me/bombo/bomboaddons/ClickLogic$ClickTarget.id:Ljava/util/UUID;
       4: aload_0
       5: invokevirtual #545                // Method java/util/UUID.equals:(Ljava/lang/Object;)Z
       8: ireturn

  static {};
    Code:
       0: new           #548                // class java/util/ArrayList
       3: dup
       4: invokespecial #549                // Method java/util/ArrayList."<init>":()V
       7: putstatic     #84                 // Field targets:Ljava/util/List;
      10: iconst_0
      11: putstatic     #155                // Field debugMode:Z
      14: new           #551                // class com/google/gson/GsonBuilder
      17: dup
      18: invokespecial #552                // Method com/google/gson/GsonBuilder."<init>":()V
      21: invokevirtual #556                // Method com/google/gson/GsonBuilder.setPrettyPrinting:()Lcom/google/gson/GsonBuilder;
      24: invokevirtual #560                // Method com/google/gson/GsonBuilder.create:()Lcom/google/gson/Gson;
      27: putstatic     #472                // Field GSON:Lcom/google/gson/Gson;
      30: invokestatic  #566                // InterfaceMethod net/fabricmc/loader/api/FabricLoader.getInstance:()Lnet/fabricmc/loader/api/FabricLoader;
      33: invokeinterface #570,  1          // InterfaceMethod net/fabricmc/loader/api/FabricLoader.getConfigDir:()Ljava/nio/file/Path;
      38: ldc_w         #572                // String bomboaddons_clicks.json
      41: invokeinterface #578,  2          // InterfaceMethod java/nio/file/Path.resolve:(Ljava/lang/String;)Ljava/nio/file/Path;
      46: invokeinterface #581,  1          // InterfaceMethod java/nio/file/Path.toFile:()Ljava/io/File;
      51: putstatic     #152                // Field CONFIG_FILE:Ljava/io/File;
      54: new           #583                // class java/util/HashMap
      57: dup
      58: invokespecial #584                // Method java/util/HashMap."<init>":()V
      61: putstatic     #62                 // Field KEY_MAP:Ljava/util/Map;
      64: iconst_0
      65: istore_0
      66: iload_0
      67: bipush        9
      69: if_icmpgt     98
      72: getstatic     #62                 // Field KEY_MAP:Ljava/util/Map;
      75: iload_0
      76: invokestatic  #586                // Method java/lang/String.valueOf:(I)Ljava/lang/String;
      79: bipush        48
      81: iload_0
      82: iadd
      83: invokestatic  #74                 // Method java/lang/Integer.valueOf:(I)Ljava/lang/Integer;
      86: invokeinterface #589,  3          // InterfaceMethod java/util/Map.put:(Ljava/lang/Object;Ljava/lang/Object;)Ljava/lang/Object;
      91: pop
      92: iinc          0, 1
      95: goto          66
      98: bipush        97
     100: istore_0
     101: iload_0
     102: bipush        122
     104: if_icmpgt     138
     107: getstatic     #62                 // Field KEY_MAP:Ljava/util/Map;
     110: iload_0
     111: invokestatic  #592                // Method java/lang/String.valueOf:(C)Ljava/lang/String;
     114: bipush        65
     116: iload_0
     117: bipush        97
     119: isub
     120: iadd
     121: invokestatic  #74                 // Method java/lang/Integer.valueOf:(I)Ljava/lang/Integer;
     124: invokeinterface #589,  3          // InterfaceMethod java/util/Map.put:(Ljava/lang/Object;Ljava/lang/Object;)Ljava/lang/Object;
     129: pop
     130: iload_0
     131: iconst_1
     132: iadd
     133: i2c
     134: istore_0
     135: goto          101
     138: getstatic     #62                 // Field KEY_MAP:Ljava/util/Map;
     141: ldc_w         #594                // String tab
     144: sipush        258
     147: invokestatic  #74                 // Method java/lang/Integer.valueOf:(I)Ljava/lang/Integer;
     150: invokeinterface #589,  3          // InterfaceMethod java/util/Map.put:(Ljava/lang/Object;Ljava/lang/Object;)Ljava/lang/Object;
     155: pop
     156: getstatic     #62                 // Field KEY_MAP:Ljava/util/Map;
     159: ldc_w         #596                // String space
     162: bipush        32
     164: invokestatic  #74                 // Method java/lang/Integer.valueOf:(I)Ljava/lang/Integer;
     167: invokeinterface #589,  3          // InterfaceMethod java/util/Map.put:(Ljava/lang/Object;Ljava/lang/Object;)Ljava/lang/Object;
     172: pop
     173: getstatic     #62                 // Field KEY_MAP:Ljava/util/Map;
     176: ldc_w         #598                // String enter
     179: sipush        257
     182: invokestatic  #74                 // Method java/lang/Integer.valueOf:(I)Ljava/lang/Integer;
     185: invokeinterface #589,  3          // InterfaceMethod java/util/Map.put:(Ljava/lang/Object;Ljava/lang/Object;)Ljava/lang/Object;
     190: pop
     191: getstatic     #62                 // Field KEY_MAP:Ljava/util/Map;
     194: ldc_w         #600                // String escape
     197: sipush        256
     200: invokestatic  #74                 // Method java/lang/Integer.valueOf:(I)Ljava/lang/Integer;
     203: invokeinterface #589,  3          // InterfaceMethod java/util/Map.put:(Ljava/lang/Object;Ljava/lang/Object;)Ljava/lang/Object;
     208: pop
     209: getstatic     #62                 // Field KEY_MAP:Ljava/util/Map;
     212: ldc_w         #602                // String backspace
     215: sipush        259
     218: invokestatic  #74                 // Method java/lang/Integer.valueOf:(I)Ljava/lang/Integer;
     221: invokeinterface #589,  3          // InterfaceMethod java/util/Map.put:(Ljava/lang/Object;Ljava/lang/Object;)Ljava/lang/Object;
     226: pop
     227: getstatic     #62                 // Field KEY_MAP:Ljava/util/Map;
     230: ldc_w         #604                // String left_shift
     233: sipush        340
     236: invokestatic  #74                 // Method java/lang/Integer.valueOf:(I)Ljava/lang/Integer;
     239: invokeinterface #589,  3          // InterfaceMethod java/util/Map.put:(Ljava/lang/Object;Ljava/lang/Object;)Ljava/lang/Object;
     244: pop
     245: getstatic     #62                 // Field KEY_MAP:Ljava/util/Map;
     248: ldc_w         #606                // String right_shift
     251: sipush        344
     254: invokestatic  #74                 // Method java/lang/Integer.valueOf:(I)Ljava/lang/Integer;
     257: invokeinterface #589,  3          // InterfaceMethod java/util/Map.put:(Ljava/lang/Object;Ljava/lang/Object;)Ljava/lang/Object;
     262: pop
     263: getstatic     #62                 // Field KEY_MAP:Ljava/util/Map;
     266: ldc_w         #608                // String left_control
     269: sipush        341
     272: invokestatic  #74                 // Method java/lang/Integer.valueOf:(I)Ljava/lang/Integer;
     275: invokeinterface #589,  3          // InterfaceMethod java/util/Map.put:(Ljava/lang/Object;Ljava/lang/Object;)Ljava/lang/Object;
     280: pop
     281: getstatic     #62                 // Field KEY_MAP:Ljava/util/Map;
     284: ldc_w         #610                // String right_control
     287: sipush        345
     290: invokestatic  #74                 // Method java/lang/Integer.valueOf:(I)Ljava/lang/Integer;
     293: invokeinterface #589,  3          // InterfaceMethod java/util/Map.put:(Ljava/lang/Object;Ljava/lang/Object;)Ljava/lang/Object;
     298: pop
     299: getstatic     #62                 // Field KEY_MAP:Ljava/util/Map;
     302: ldc_w         #612                // String left_alt
     305: sipush        342
     308: invokestatic  #74                 // Method java/lang/Integer.valueOf:(I)Ljava/lang/Integer;
     311: invokeinterface #589,  3          // InterfaceMethod java/util/Map.put:(Ljava/lang/Object;Ljava/lang/Object;)Ljava/lang/Object;
     316: pop
     317: getstatic     #62                 // Field KEY_MAP:Ljava/util/Map;
     320: ldc_w         #614                // String right_alt
     323: sipush        346
     326: invokestatic  #74                 // Method java/lang/Integer.valueOf:(I)Ljava/lang/Integer;
     329: invokeinterface #589,  3          // InterfaceMethod java/util/Map.put:(Ljava/lang/Object;Ljava/lang/Object;)Ljava/lang/Object;
     334: pop
     335: getstatic     #62                 // Field KEY_MAP:Ljava/util/Map;
     338: ldc_w         #616                // String insert
     341: sipush        260
     344: invokestatic  #74                 // Method java/lang/Integer.valueOf:(I)Ljava/lang/Integer;
     347: invokeinterface #589,  3          // InterfaceMethod java/util/Map.put:(Ljava/lang/Object;Ljava/lang/Object;)Ljava/lang/Object;
     352: pop
     353: getstatic     #62                 // Field KEY_MAP:Ljava/util/Map;
     356: ldc_w         #618                // String delete
     359: sipush        261
     362: invokestatic  #74                 // Method java/lang/Integer.valueOf:(I)Ljava/lang/Integer;
     365: invokeinterface #589,  3          // InterfaceMethod java/util/Map.put:(Ljava/lang/Object;Ljava/lang/Object;)Ljava/lang/Object;
     370: pop
     371: getstatic     #62                 // Field KEY_MAP:Ljava/util/Map;
     374: ldc_w         #411                // String right
     377: sipush        262
     380: invokestatic  #74                 // Method java/lang/Integer.valueOf:(I)Ljava/lang/Integer;
     383: invokeinterface #589,  3          // InterfaceMethod java/util/Map.put:(Ljava/lang/Object;Ljava/lang/Object;)Ljava/lang/Object;
     388: pop
     389: getstatic     #62                 // Field KEY_MAP:Ljava/util/Map;
     392: ldc_w         #620                // String left
     395: sipush        263
     398: invokestatic  #74                 // Method java/lang/Integer.valueOf:(I)Ljava/lang/Integer;
     401: invokeinterface #589,  3          // InterfaceMethod java/util/Map.put:(Ljava/lang/Object;Ljava/lang/Object;)Ljava/lang/Object;
     406: pop
     407: getstatic     #62                 // Field KEY_MAP:Ljava/util/Map;
     410: ldc_w         #622                // String down
     413: sipush        264
     416: invokestatic  #74                 // Method java/lang/Integer.valueOf:(I)Ljava/lang/Integer;
     419: invokeinterface #589,  3          // InterfaceMethod java/util/Map.put:(Ljava/lang/Object;Ljava/lang/Object;)Ljava/lang/Object;
     424: pop
     425: getstatic     #62                 // Field KEY_MAP:Ljava/util/Map;
     428: ldc_w         #624                // String up
     431: sipush        265
     434: invokestatic  #74                 // Method java/lang/Integer.valueOf:(I)Ljava/lang/Integer;
     437: invokeinterface #589,  3          // InterfaceMethod java/util/Map.put:(Ljava/lang/Object;Ljava/lang/Object;)Ljava/lang/Object;
     442: pop
     443: getstatic     #62                 // Field KEY_MAP:Ljava/util/Map;
     446: ldc_w         #626                // String page_up
     449: sipush        266
     452: invokestatic  #74                 // Method java/lang/Integer.valueOf:(I)Ljava/lang/Integer;
     455: invokeinterface #589,  3          // InterfaceMethod java/util/Map.put:(Ljava/lang/Object;Ljava/lang/Object;)Ljava/lang/Object;
     460: pop
     461: getstatic     #62                 // Field KEY_MAP:Ljava/util/Map;
     464: ldc_w         #628                // String page_down
     467: sipush        267
     470: invokestatic  #74                 // Method java/lang/Integer.valueOf:(I)Ljava/lang/Integer;
     473: invokeinterface #589,  3          // InterfaceMethod java/util/Map.put:(Ljava/lang/Object;Ljava/lang/Object;)Ljava/lang/Object;
     478: pop
     479: getstatic     #62                 // Field KEY_MAP:Ljava/util/Map;
     482: ldc_w         #630                // String home
     485: sipush        268
     488: invokestatic  #74                 // Method java/lang/Integer.valueOf:(I)Ljava/lang/Integer;
     491: invokeinterface #589,  3          // InterfaceMethod java/util/Map.put:(Ljava/lang/Object;Ljava/lang/Object;)Ljava/lang/Object;
     496: pop
     497: getstatic     #62                 // Field KEY_MAP:Ljava/util/Map;
     500: ldc_w         #632                // String end
     503: sipush        269
     506: invokestatic  #74                 // Method java/lang/Integer.valueOf:(I)Ljava/lang/Integer;
     509: invokeinterface #589,  3          // InterfaceMethod java/util/Map.put:(Ljava/lang/Object;Ljava/lang/Object;)Ljava/lang/Object;
     514: pop
     515: getstatic     #62                 // Field KEY_MAP:Ljava/util/Map;
     518: ldc_w         #634                // String caps_lock
     521: sipush        280
     524: invokestatic  #74                 // Method java/lang/Integer.valueOf:(I)Ljava/lang/Integer;
     527: invokeinterface #589,  3          // InterfaceMethod java/util/Map.put:(Ljava/lang/Object;Ljava/lang/Object;)Ljava/lang/Object;
     532: pop
     533: getstatic     #62                 // Field KEY_MAP:Ljava/util/Map;
     536: ldc_w         #636                // String scroll_lock
     539: sipush        281
     542: invokestatic  #74                 // Method java/lang/Integer.valueOf:(I)Ljava/lang/Integer;
     545: invokeinterface #589,  3          // InterfaceMethod java/util/Map.put:(Ljava/lang/Object;Ljava/lang/Object;)Ljava/lang/Object;
     550: pop
     551: getstatic     #62                 // Field KEY_MAP:Ljava/util/Map;
     554: ldc_w         #638                // String num_lock
     557: sipush        282
     560: invokestatic  #74                 // Method java/lang/Integer.valueOf:(I)Ljava/lang/Integer;
     563: invokeinterface #589,  3          // InterfaceMethod java/util/Map.put:(Ljava/lang/Object;Ljava/lang/Object;)Ljava/lang/Object;
     568: pop
     569: getstatic     #62                 // Field KEY_MAP:Ljava/util/Map;
     572: ldc_w         #640                // String print_screen
     575: sipush        283
     578: invokestatic  #74                 // Method java/lang/Integer.valueOf:(I)Ljava/lang/Integer;
     581: invokeinterface #589,  3          // InterfaceMethod java/util/Map.put:(Ljava/lang/Object;Ljava/lang/Object;)Ljava/lang/Object;
     586: pop
     587: getstatic     #62                 // Field KEY_MAP:Ljava/util/Map;
     590: ldc_w         #642                // String pause
     593: sipush        284
     596: invokestatic  #74                 // Method java/lang/Integer.valueOf:(I)Ljava/lang/Integer;
     599: invokeinterface #589,  3          // InterfaceMethod java/util/Map.put:(Ljava/lang/Object;Ljava/lang/Object;)Ljava/lang/Object;
     604: pop
     605: iconst_1
     606: istore_0
     607: iload_0
     608: bipush        12
     610: if_icmpgt     644
     613: getstatic     #62                 // Field KEY_MAP:Ljava/util/Map;
     616: iload_0
     617: invokedynamic #646,  0            // InvokeDynamic #13:makeConcatWithConstants:(I)Ljava/lang/String;
     622: sipush        290
     625: iload_0
     626: iadd
     627: iconst_1
     628: isub
     629: invokestatic  #74                 // Method java/lang/Integer.valueOf:(I)Ljava/lang/Integer;
     632: invokeinterface #589,  3          // InterfaceMethod java/util/Map.put:(Ljava/lang/Object;Ljava/lang/Object;)Ljava/lang/Object;
     637: pop
     638: iinc          0, 1
     641: goto          607
     644: iconst_0
     645: istore_0
     646: iload_0
     647: bipush        9
     649: if_icmpgt     681
     652: getstatic     #62                 // Field KEY_MAP:Ljava/util/Map;
     655: iload_0
     656: invokedynamic #649,  0            // InvokeDynamic #14:makeConcatWithConstants:(I)Ljava/lang/String;
     661: sipush        320
     664: iload_0
     665: iadd
     666: invokestatic  #74                 // Method java/lang/Integer.valueOf:(I)Ljava/lang/Integer;
     669: invokeinterface #589,  3          // InterfaceMethod java/util/Map.put:(Ljava/lang/Object;Ljava/lang/Object;)Ljava/lang/Object;
     674: pop
     675: iinc          0, 1
     678: goto          646
     681: invokestatic  #651                // Method loadTargets:()V
     684: return
}
