Compiled from "SignEditMixin.java"
public abstract class me.bombo.bomboaddons.mixin.SignEditMixin {
  private java.lang.String[] field_40425;

  private int field_40428;

  public me.bombo.bomboaddons.mixin.SignEditMixin();
    Code:
       0: aload_0
       1: invokespecial #28                 // Method java/lang/Object."<init>":()V
       4: return

  private void onInit(org.spongepowered.asm.mixin.injection.callback.CallbackInfo);
    Code:
       0: getstatic     #45                 // Field me/bombo/bomboaddons/Bomboaddons.LOGGER:Lorg/slf4j/Logger;
       3: ldc           #47                 // String SignEditScreen initialized
       5: invokeinterface #53,  2           // InterfaceMethod org/slf4j/Logger.info:(Ljava/lang/String;)V
      10: return

  private void onDone(org.spongepowered.asm.mixin.injection.callback.CallbackInfo);
    Code:
       0: invokestatic  #61                 // Method me/bombo/bomboaddons/BomboConfig.get:()Lme/bombo/bomboaddons/BomboConfig$Settings;
       3: getfield      #65                 // Field me/bombo/bomboaddons/BomboConfig$Settings.signCalculator:Z
       6: ifne          10
       9: return
      10: iconst_0
      11: istore_2
      12: iload_2
      13: aload_0
      14: getfield      #67                 // Field field_40425:[Ljava/lang/String;
      17: arraylength
      18: if_icmpge     63
      21: aload_0
      22: getfield      #67                 // Field field_40425:[Ljava/lang/String;
      25: iload_2
      26: aaload
      27: ifnull        57
      30: aload_0
      31: getfield      #67                 // Field field_40425:[Ljava/lang/String;
      34: iload_2
      35: aaload
      36: invokevirtual #73                 // Method java/lang/String.isEmpty:()Z
      39: ifne          57
      42: aload_0
      43: getfield      #67                 // Field field_40425:[Ljava/lang/String;
      46: iload_2
      47: aload_0
      48: getfield      #67                 // Field field_40425:[Ljava/lang/String;
      51: iload_2
      52: aaload
      53: invokestatic  #79                 // Method me/bombo/bomboaddons/SignCalculator.calculate:(Ljava/lang/String;)Ljava/lang/String;
      56: aastore
      57: iinc          2, 1
      60: goto          12
      63: return

  private void onRender(net.minecraft.class_332, int, int, float, org.spongepowered.asm.mixin.injection.callback.CallbackInfo);
    Code:
       0: invokestatic  #61                 // Method me/bombo/bomboaddons/BomboConfig.get:()Lme/bombo/bomboaddons/BomboConfig$Settings;
       3: getfield      #65                 // Field me/bombo/bomboaddons/BomboConfig$Settings.signCalculator:Z
       6: ifne          10
       9: return
      10: invokestatic  #93                 // Method net/minecraft/class_310.method_1551:()Lnet/minecraft/class_310;
      13: astore        6
      15: aload         6
      17: invokevirtual #97                 // Method net/minecraft/class_310.method_22683:()Lnet/minecraft/class_1041;
      20: invokevirtual #103                // Method net/minecraft/class_1041.method_4486:()I
      23: istore        7
      25: iload         7
      27: iconst_2
      28: idiv
      29: istore        8
      31: bipush        55
      33: istore        9
      35: aload_0
      36: getfield      #67                 // Field field_40425:[Ljava/lang/String;
      39: aload_0
      40: getfield      #105                // Field field_40428:I
      43: aaload
      44: astore        10
      46: aload         10
      48: ifnull        154
      51: aload         10
      53: invokevirtual #73                 // Method java/lang/String.isEmpty:()Z
      56: ifne          154
      59: aload         10
      61: invokestatic  #109                // Method me/bombo/bomboaddons/SignCalculator.isPotentialExpression:(Ljava/lang/String;)Z
      64: ifeq          154
      67: aload         10
      69: invokestatic  #112                // Method me/bombo/bomboaddons/SignCalculator.getPreviewText:(Ljava/lang/String;)Ljava/lang/String;
      72: astore        11
      74: aload         10
      76: invokestatic  #115                // Method me/bombo/bomboaddons/SignCalculator.isValidExpression:(Ljava/lang/String;)Z
      79: istore        12
      81: iload         12
      83: ifeq          91
      86: ldc           #117                // String §a
      88: goto          93
      91: ldc           #123                // String §c
      93: astore        13
      95: iload         12
      97: ifne          109
     100: aload         10
     102: invokedynamic #134,  0            // InvokeDynamic #0:makeConcatWithConstants:(Ljava/lang/String;)Ljava/lang/String;
     107: astore        11
     109: aload         13
     111: aload         11
     113: invokedynamic #139,  0            // InvokeDynamic #1:makeConcatWithConstants:(Ljava/lang/String;Ljava/lang/String;)Ljava/lang/String;
     118: astore        14
     120: aload         6
     122: getfield      #143                // Field net/minecraft/class_310.field_1772:Lnet/minecraft/class_327;
     125: aload         14
     127: invokevirtual #149                // Method net/minecraft/class_327.method_1727:(Ljava/lang/String;)I
     130: istore        15
     132: aload_1
     133: aload         6
     135: getfield      #143                // Field net/minecraft/class_310.field_1772:Lnet/minecraft/class_327;
     138: aload         14
     140: iload         8
     142: iload         15
     144: iconst_2
     145: idiv
     146: isub
     147: iload         9
     149: iconst_m1
     150: iconst_1
     151: invokevirtual #153                // Method net/minecraft/class_332.method_51433:(Lnet/minecraft/class_327;Ljava/lang/String;IIIZ)V
     154: dconst_0
     155: dstore        11
     157: iconst_0
     158: istore        13
     160: aload_0
     161: getfield      #67                 // Field field_40425:[Ljava/lang/String;
     164: astore        14
     166: aload         14
     168: arraylength
     169: istore        15
     171: iconst_0
     172: istore        16
     174: iload         16
     176: iload         15
     178: if_icmpge     215
     181: aload         14
     183: iload         16
     185: aaload
     186: astore        17
     188: aload         17
     190: invokestatic  #115                // Method me/bombo/bomboaddons/SignCalculator.isValidExpression:(Ljava/lang/String;)Z
     193: ifeq          209
     196: dload         11
     198: aload         17
     200: invokestatic  #158                // Method me/bombo/bomboaddons/SignCalculator.getResult:(Ljava/lang/String;)D
     203: dadd
     204: dstore        11
     206: iconst_1
     207: istore        13
     209: iinc          16, 1
     212: goto          174
     215: iload         13
     217: ifeq          269
     220: dload         11
     222: invokestatic  #162                // Method me/bombo/bomboaddons/SignCalculator.formatResultOnly:(D)Ljava/lang/String;
     225: invokedynamic #165,  0            // InvokeDynamic #2:makeConcatWithConstants:(Ljava/lang/String;)Ljava/lang/String;
     230: astore        14
     232: aload         6
     234: getfield      #143                // Field net/minecraft/class_310.field_1772:Lnet/minecraft/class_327;
     237: aload         14
     239: invokevirtual #149                // Method net/minecraft/class_327.method_1727:(Ljava/lang/String;)I
     242: istore        15
     244: aload_1
     245: aload         6
     247: getfield      #143                // Field net/minecraft/class_310.field_1772:Lnet/minecraft/class_327;
     250: aload         14
     252: iload         8
     254: iload         15
     256: iconst_2
     257: idiv
     258: isub
     259: iload         9
     261: bipush        30
     263: isub
     264: iconst_m1
     265: iconst_1
     266: invokevirtual #153                // Method net/minecraft/class_332.method_51433:(Lnet/minecraft/class_327;Ljava/lang/String;IIIZ)V
     269: return
}
